{
  "validatorTargets": [
    {
      "votePubkey": "CwSZ17woioM2bqEbaswZJYvx5pemN6t3shBcU6zqPHyG",
      "delta": "1142242277297",
      "existingStake": "10435803004373",
      "existingActiveStake": "10435803004373",
      "targetStake": {
        "directed": "855515912246",
        "undirectedWhitelist": "10722529369424"
      },
      "targetTotalStake": "11578045281670"
    },
    {
      "votePubkey": "gangtRyGPTvYWb8K3xS2feJQaCks4iJ7rytFUPtVqSY",
      "delta": "583488751843",
      "existingStake": "10139040617581",
      "existingActiveStake": "10139040617581",
      "targetStake": {
        "directed": "0",
        "undirectedWhitelist": "10722529369424"
      },
      "targetTotalStake": "10722529369424"
    },
    {
      "votePubkey": "J1to3PQfXidUUhprQWgdKkQAMWPJAEqSJ7amkBDE9qhF",
      "delta": "-886459219723",
      "existingStake": "11669293932432",
      "existingActiveStake": "11669293932432",
      "targetStake": {
        "directed": "60305343285",
        "undirectedWhitelist": "10722529369424"
      },
      "targetTotalStake": "10782834712709"
    },
    {
      "votePubkey": "2ayMCC4aizr8RGg5ptXYqu8uoxW1whNek1hE1zaAd58z",
      "delta": "315848103950",
      "existingStake": "10406681265474",
      "existingActiveStake": "10406681265474",
      "targetStake": {
        "directed": "0",
        "undirectedWhitelist": "10722529369424"
      },
      "targetTotalStake": "10722529369424"
    },
    {
      "votePubkey": "7K8DVxtNJGnMtUY1CQJT5jcs8sFGSZTDiG7kowvFpECh",
      "delta": "1005611035624",
      "existingStake": "10502210979258",
      "existingActiveStake": "10502210979258",
      "targetStake": {
        "directed": "785292645458",
        "undirectedWhitelist": "10722529369424"
      },
      "targetTotalStake": "11507822014882"
    },
    {
      "votePubkey": "Ehdn9LdjTAURQSMoDPERXLehtvzy7QD762wwPkzGT7RS",
      "delta": "386989821575",
      "existingStake": "10335539547849",
      "existingActiveStake": "10335539547849",
      "targetStake": {
        "directed": "0",
        "undirectedWhitelist": "10722529369424"
      },
      "targetTotalStake": "10722529369424"
    },
    {
      "votePubkey": "GA2t11gJcmuZ4y7pShTzgYDkxVaJaVQJqkVUqojhPPsT",
      "delta": "429721760150",
      "existingStake": "10820120159842",
      "existingActiveStake": "10820120159842",
      "targetStake": {
        "directed": "527312550568",
        "undirectedWhitelist": "10722529369424"
      },
      "targetTotalStake": "11249841919992"
    },
    {
      "votePubkey": "DfpdmTsSCBPxCDwZwgBMfjjV8mF8xHkGRcXP8dJBVmrq",
      "delta": "387382077359",
      "existingStake": "10335147496462",
      "existingActiveStake": "10335147496462",
      "targetStake": {
        "directed": "204397",
        "undirectedWhitelist": "10722529369424"
      },
      "targetTotalStake": "10722529573821"
    },
    {
      "votePubkey": "StepeLdhJ2znRjHcZdjwMWsC4nTRURNKQY8Nca82LJp",
      "delta": "1135861485500",
      "existingStake": "337091094832011",
      "existingActiveStake": "337091094832011",
      "targetStake": {
        "directed": "327504426948087",
        "undirectedWhitelist": "10722529369424"
      },
      "targetTotalStake": "338226956317511"
    },
    {
      "votePubkey": "B1w6SZcyvjyp6zEyStcc8u9AxXAh2AbYvNzMmP9rRKE9",
      "delta": "474354508330",
      "existingStake": "22518440151792",
      "existingActiveStake": "22518440151792",
      "targetStake": {
        "directed": "12270265290698",
        "undirectedWhitelist": "10722529369424"
      },
      "targetTotalStake": "22992794660122"
    },
    {
      "votePubkey": "mesh3Px7WMi7Dkxke4ZZBULoKHM6sp37wKtg4DwPqPY",
      "delta": "597964833562",
      "existingStake": "10566663045614",
      "existingActiveStake": "10566663045614",
      "targetStake": {
        "directed": "442098509752",
        "undirectedWhitelist": "10722529369424"
      },
      "targetTotalStake": "11164627879176"
    },
    {
      "votePubkey": "2ZiMfQaT59j86HVWCvspuMtBotnVBeTc3BKk3kKpwgKP",
      "delta": "1239755457291",
      "existingStake": "9482773912133",
      "existingActiveStake": "9482773912133",
      "targetStake": {
        "directed": "0",
        "undirectedWhitelist": "10722529369424"
      },
      "targetTotalStake": "10722529369424"
    },
    {
      "votePubkey": "gridZ5cMHjWGktAQt6o36NtF7XSv19nJBrW83zmo7BM",
      "delta": "317223982080",
      "existingStake": "10842667510402",
      "existingActiveStake": "10842667510402",
      "targetStake": {
        "directed": "437362123058",
        "undirectedWhitelist": "10722529369424"
      },
      "targetTotalStake": "11159891492482"
    },
    {
      "votePubkey": "radYEig9KGrMTMWbWRFV7LStotQbnLgPaEFHVDsudQz",
      "delta": "567597894462",
      "existingStake": "10154931474962",
      "existingActiveStake": "10154931474962",
      "targetStake": {
        "directed": "0",
        "undirectedWhitelist": "10722529369424"
      },
      "targetTotalStake": "10722529369424"
    },
    {
      "votePubkey": "phz34EcgWRCT9otPzRS2JtSzVHxQJk4SovqJvV1TQk8",
      "delta": "386964212049",
      "existingStake": "10335565157375",
      "existingActiveStake": "10335565157375",
      "targetStake": {
        "directed": "0",
        "undirectedWhitelist": "10722529369424"
      },
      "targetTotalStake": "10722529369424"
    },
    {
      "votePubkey": "Ac1beBKixfNdrTAac7GRaTsJTxLyvgGvJjvy4qQfvyfc",
      "delta": "1225829097585",
      "existingStake": "9533324595243",
      "existingActiveStake": "9533324595243",
      "targetStake": {
        "directed": "36624323404",
        "undirectedWhitelist": "10722529369424"
      },
      "targetTotalStake": "10759153692828"
    },
    {
      "votePubkey": "MNDE6ueF5uMvyk3ohq7wWZ8H749pbpj1yHj2MvMRCJM",
      "delta": "384434696453",
      "existingStake": "10338094672971",
      "existingActiveStake": "10338094672971",
      "targetStake": {
        "directed": "0",
        "undirectedWhitelist": "10722529369424"
      },
      "targetTotalStake": "10722529369424"
    },
    {
      "votePubkey": "Luna8BkZNpZ9DKmszrZYPvFpTr4eJJfxxTnGDwTrYkv",
      "delta": "315815507472",
      "existingStake": "10473092955057",
      "existingActiveStake": "10473092955057",
      "targetStake": {
        "directed": "66379093104",
        "undirectedWhitelist": "10722529369424"
      },
      "targetTotalStake": "10788908462529"
    },
    {
      "votePubkey": "vvvvXsU6iG2enDVvs4KeVqS4YrZczTujSv5p3dSeNHx",
      "delta": "317310935980",
      "existingStake": "10407757026815",
      "existingActiveStake": "10407757026815",
      "targetStake": {
        "directed": "2538593371",
        "undirectedWhitelist": "10722529369424"
      },
      "targetTotalStake": "10725067962795"
    },
    {
      "votePubkey": "7JZTyHRTmzHfmHH89uT9xKSKDVJ1VnNQ1FeTeM4iH3J2",
      "delta": "6181956892",
      "existingStake": "10716347412532",
      "existingActiveStake": "1680550707",
      "targetStake": {
        "directed": "0",
        "undirectedWhitelist": "10722529369424"
      },
      "targetTotalStake": "10722529369424"
    },
    {
      "votePubkey": "3xjfK9C9YNcta8MvK1US4sQ3bc6DEjoJoR3qLExGf9xE",
      "delta": "270492378200",
      "existingStake": "10452814099147",
      "existingActiveStake": "10452814099147",
      "targetStake": {
        "directed": "777107923",
        "undirectedWhitelist": "10722529369424"
      },
      "targetTotalStake": "10723306477347"
    },
    {
      "votePubkey": "votem3UdGx5xWFbY9EFbyZ1X2pBuswfR5yd2oB3JAaj",
      "delta": "569303217412",
      "existingStake": "10153226152012",
      "existingActiveStake": "10153226152012",
      "targetStake": {
        "directed": "0",
        "undirectedWhitelist": "10722529369424"
      },
      "targetTotalStake": "10722529369424"
    },
    {
      "votePubkey": "DvFTFLrEQSfEadPQdesvf5bpYWYqXK9iaJAjq95piQBs",
      "delta": "384393243372",
      "existingStake": "10338136126052",
      "existingActiveStake": "10338136126052",
      "targetStake": {
        "directed": "0",
        "undirectedWhitelist": "10722529369424"
      },
      "targetTotalStake": "10722529369424"
    },
    {
      "votePubkey": "fVotEjqpmpQYgyVyBCwYm62BKqqTQNE6SpYnRmdBazH",
      "delta": "387250445063",
      "existingStake": "10335284637576",
      "existingActiveStake": "10335284637576",
      "targetStake": {
        "directed": "5713215",
        "undirectedWhitelist": "10722529369424"
      },
      "targetTotalStake": "10722535082639"
    },
    {
      "votePubkey": "sTach38ebT8jnGH8i2D1g8NDAS6An19whVMnSSWPXt4",
      "delta": "584361451594",
      "existingStake": "10138167917830",
      "existingActiveStake": "10138167917830",
      "targetStake": {
        "directed": "0",
        "undirectedWhitelist": "10722529369424"
      },
      "targetTotalStake": "10722529369424"
    },
    {
      "votePubkey": "8DHFGo3fDB8GudbNLZEyExLzXQPwvY4twybPbxwDnffx",
      "delta": "38692815822",
      "existingStake": "10683836553602",
      "existingActiveStake": "10683836553602",
      "targetStake": {
        "directed": "0",
        "undirectedWhitelist": "10722529369424"
      },
      "targetTotalStake": "10722529369424"
    },
    {
      "votePubkey": "DG6fVEB2Qy1jntvHVPui3R12CMqcwNNnjYPYdsbQ9ACP",
      "delta": "386987701049",
      "existingStake": "10335541668375",
      "existingActiveStake": "10335541668375",
      "targetStake": {
        "directed": "0",
        "undirectedWhitelist": "10722529369424"
      },
      "targetTotalStake": "10722529369424"
    },
    {
      "votePubkey": "4m1PbxzwLdUnEwog3T9UKxgjktgriHgE1CfAhMqDw7Xx",
      "delta": "997139619686",
      "existingStake": "11818405835946",
      "existingActiveStake": "11818405835946",
      "targetStake": {
        "directed": "2093016086208",
        "undirectedWhitelist": "10722529369424"
      },
      "targetTotalStake": "12815545455632"
    },
    {
      "votePubkey": "3dXXxEaV4fZqw1PL7VezfDkiJV5W4WTtRjh2EHgKSthF",
      "delta": "387148844891",
      "existingStake": "10335380524533",
      "existingActiveStake": "10335380524533",
      "targetStake": {
        "directed": "0",
        "undirectedWhitelist": "10722529369424"
      },
      "targetTotalStake": "10722529369424"
    },
    {
      "votePubkey": "EtMSc3MvcDXUr6ChK5GxyFVwTxYA3zqP5XzjE9jwKvSV",
      "delta": "313922512927",
      "existingStake": "63562270029385",
      "existingActiveStake": "63562270029385",
      "targetStake": {
        "directed": "53153663172888",
        "undirectedWhitelist": "10722529369424"
      },
      "targetTotalStake": "63876192542312"
    },
    {
      "votePubkey": "hxVjzDmta9TuN1gM981TRKnfwG2uZ9TQDGwSCs3uDow",
      "delta": "384400387919",
      "existingStake": "10338128981505",
      "existingActiveStake": "10338128981505",
      "targetStake": {
        "directed": "0",
        "undirectedWhitelist": "10722529369424"
      },
      "targetTotalStake": "10722529369424"
    },
    {
      "votePubkey": "VotESBSkLKU8vebS6wTR2rzWWJsLc6YThYS6tebPxXq",
      "delta": "579827812080",
      "existingStake": "10149797219752",
      "existingActiveStake": "10149797219752",
      "targetStake": {
        "directed": "7095662408",
        "undirectedWhitelist": "10722529369424"
      },
      "targetTotalStake": "10729625031832"
    },
    {
      "votePubkey": "86Sw9R6ynPmXnHfwUWinXtq1QoF2KHesfQQyZG5r8sXo",
      "delta": "434490257530",
      "existingStake": "10292338546076",
      "existingActiveStake": "10292338546076",
      "targetStake": {
        "directed": "4299434182",
        "undirectedWhitelist": "10722529369424"
      },
      "targetTotalStake": "10726828803606"
    },
    {
      "votePubkey": "5AC692spnjbegP7ttCXJEzUe8S81sLYsqJd8Ae6Zv1xU",
      "delta": "578753029045",
      "existingStake": "10232166300824",
      "existingActiveStake": "10232166300824",
      "targetStake": {
        "directed": "88389960445",
        "undirectedWhitelist": "10722529369424"
      },
      "targetTotalStake": "10810919329869"
    },
    {
      "votePubkey": "o27rnqfNHPwHsRp2xPXXwWzn2q2dGxn6UD4Rt5KMU5h",
      "delta": "359168964406",
      "existingStake": "10363360405018",
      "existingActiveStake": "10363360405018",
      "targetStake": {
        "directed": "0",
        "undirectedWhitelist": "10722529369424"
      },
      "targetTotalStake": "10722529369424"
    },
    {
      "votePubkey": "FACqsS19VScz8oo2YhdMg35EsAy6xsCZ9Y58eJXGv8QJ",
      "delta": "577834220025",
      "existingStake": "10144695149399",
      "existingActiveStake": "10144695149399",
      "targetStake": {
        "directed": "0",
        "undirectedWhitelist": "10722529369424"
      },
      "targetTotalStake": "10722529369424"
    },
    {
      "votePubkey": "SBLZib4npE7svxFA7AsD3ytdQAfYNb39c8zsU82AA2E",
      "delta": "384505697309",
      "existingStake": "10338023672115",
      "existingActiveStake": "10338023672115",
      "targetStake": {
        "directed": "0",
        "undirectedWhitelist": "10722529369424"
      },
      "targetTotalStake": "10722529369424"
    },
    {
      "votePubkey": "rapxbkwBSSvtqRFrsY83f51oUuZNuVXci74MuzYhiCy",
      "delta": "574173229222",
      "existingStake": "10148356140202",
      "existingActiveStake": "10148356140202",
      "targetStake": {
        "directed": "0",
        "undirectedWhitelist": "10722529369424"
      },
      "targetTotalStake": "10722529369424"
    },
    {
      "votePubkey": "Gvt8s5Bwnhg4G27VbnT1Zkfh7Jsztq6CNvZcc5anPonS",
      "delta": "384412878659",
      "existingStake": "10338150740956",
      "existingActiveStake": "10338150740956",
      "targetStake": {
        "directed": "34250191",
        "undirectedWhitelist": "10722529369424"
      },
      "targetTotalStake": "10722563619615"
    },
    {
      "votePubkey": "GiXx1mwSR44Tz96CaDqoadzAhZgZv7e3yZshqUwiEwwh",
      "delta": "597995146945",
      "existingStake": "10124534222479",
      "existingActiveStake": "10124534222479",
      "targetStake": {
        "directed": "0",
        "undirectedWhitelist": "10722529369424"
      },
      "targetTotalStake": "10722529369424"
    },
    {
      "votePubkey": "9Gko8QZBbV5SrEvHKtQHcMrGGSfgFP3KJUozEGifu25x",
      "delta": "315237857100",
      "existingStake": "10410849402554",
      "existingActiveStake": "10410849402554",
      "targetStake": {
        "directed": "3557890229",
        "undirectedWhitelist": "10722529369424"
      },
      "targetTotalStake": "10726087259654"
    },
    {
      "votePubkey": "sagasJDjjAHND4hien3bbo5xXkzCT5Ss6nKjyUJ45aw",
      "delta": "568817415963",
      "existingStake": "10404465521880",
      "existingActiveStake": "10404465521880",
      "targetStake": {
        "directed": "250753568418",
        "undirectedWhitelist": "10722529369424"
      },
      "targetTotalStake": "10973282937843"
    },
    {
      "votePubkey": "goJiRADNdmfnJ4iWEyft7KaYMPTVsRba2Ee1akDEBXb",
      "delta": "578748584301",
      "existingStake": "10143780785123",
      "existingActiveStake": "10143780785123",
      "targetStake": {
        "directed": "0",
        "undirectedWhitelist": "10722529369424"
      },
      "targetTotalStake": "10722529369424"
    },
    {
      "votePubkey": "DzQHN1oTdN85Sbku2bc9Fu9yEwrgRMiu2XbRcntZ31yb",
      "delta": "387096922212",
      "existingStake": "10335432447212",
      "existingActiveStake": "10335432447212",
      "targetStake": {
        "directed": "0",
        "undirectedWhitelist": "10722529369424"
      },
      "targetTotalStake": "10722529369424"
    },
    {
      "votePubkey": "323d4ZiSqS1PwGwpJwD88jNPaGqkm7YYW2tJt2T8iFzo",
      "delta": "384392792268",
      "existingStake": "10338136577156",
      "existingActiveStake": "10338136577156",
      "targetStake": {
        "directed": "0",
        "undirectedWhitelist": "10722529369424"
      },
      "targetTotalStake": "10722529369424"
    },
    {
      "votePubkey": "6JfBwvcz5QUKQJ37BMKTLrf968DDJBtwoZLw19aHwFtQ",
      "delta": "1297284169417",
      "existingStake": "10083162962694",
      "existingActiveStake": "10083162962694",
      "targetStake": {
        "directed": "657917762687",
        "undirectedWhitelist": "10722529369424"
      },
      "targetTotalStake": "11380447132111"
    },
    {
      "votePubkey": "5iZ5PQPy5Z9XDnkfoWPi6nvUgtxWnRFwZ36WaftPuaVM",
      "delta": "382998131808",
      "existingStake": "17685969241049",
      "existingActiveStake": "17685969241049",
      "targetStake": {
        "directed": "7346438003433",
        "undirectedWhitelist": "10722529369424"
      },
      "targetTotalStake": "18068967372857"
    },
    {
      "votePubkey": "EfnywDKqArxK6N6FS9ctsuzNdxfx3pzfXEQE5EevQ1SV",
      "delta": "576316743819",
      "existingStake": "21846666422747",
      "existingActiveStake": "21846666422747",
      "targetStake": {
        "directed": "11700453797142",
        "undirectedWhitelist": "10722529369424"
      },
      "targetTotalStake": "22422983166566"
    },
    {
      "votePubkey": "xLabsqDpN9WHXEXSJXk1yhqh5H8BgcqiBP1CR6Mkjcb",
      "delta": "387099445440",
      "existingStake": "10335429923984",
      "existingActiveStake": "10335429923984",
      "targetStake": {
        "directed": "0",
        "undirectedWhitelist": "10722529369424"
      },
      "targetTotalStake": "10722529369424"
    },
    {
      "votePubkey": "BeSov1og3sEYyH9JY3ap7QcQDvVX8f4sugfNPf9YLkcV",
      "delta": "311619033996",
      "existingStake": "10410910335428",
      "existingActiveStake": "10410910335428",
      "targetStake": {
        "directed": "0",
        "undirectedWhitelist": "10722529369424"
      },
      "targetTotalStake": "10722529369424"
    },
    {
      "votePubkey": "9Q1cWVFNc4UgU7dyFy29mUyeDnNZWSDaJKYVAR5jLpaK",
      "delta": "383864783102",
      "existingStake": "10338664586322",
      "existingActiveStake": "10338664586322",
      "targetStake": {
        "directed": "0",
        "undirectedWhitelist": "10722529369424"
      },
      "targetTotalStake": "10722529369424"
    },
    {
      "votePubkey": "adraBKLNY3DL3pg6SJRDYiMA8BsznaWpUdE42X41gbP",
      "delta": "585691613467",
      "existingStake": "10141864470616",
      "existingActiveStake": "10141864470616",
      "targetStake": {
        "directed": "5026714658",
        "undirectedWhitelist": "10722529369424"
      },
      "targetTotalStake": "10727556084083"
    },
    {
      "votePubkey": "wetwJSUHT5afX3gP49q75gkz8FcCfvsw2kuSQ1UjT9R",
      "delta": "386912900345",
      "existingStake": "10335616469079",
      "existingActiveStake": "10335616469079",
      "targetStake": {
        "directed": "0",
        "undirectedWhitelist": "10722529369424"
      },
      "targetTotalStake": "10722529369424"
    },
    {
      "votePubkey": "dedxrPfNqPKBRmUyP9LDkaitpQzU6PD44jA6GP9Ndhk",
      "delta": "384182724835",
      "existingStake": "10338346644589",
      "existingActiveStake": "10338346644589",
      "targetStake": {
        "directed": "0",
        "undirectedWhitelist": "10722529369424"
      },
      "targetTotalStake": "10722529369424"
    },
    {
      "votePubkey": "G1EAMrJcvzs5SwqAQRgDTjYBEGrxxJVwNS7qiUtB3akg",
      "delta": "384392963200",
      "existingStake": "10338136406224",
      "existingActiveStake": "10338136406224",
      "targetStake": {
        "directed": "0",
        "undirectedWhitelist": "10722529369424"
      },
      "targetTotalStake": "10722529369424"
    },
    {
      "votePubkey": "EJHf5N9is5spAF5Kz384tTvTV3CwTka6qzUoZrYm53SV",
      "delta": "580870543457",
      "existingStake": "10141658825967",
      "existingActiveStake": "10141658825967",
      "targetStake": {
        "directed": "0",
        "undirectedWhitelist": "10722529369424"
      },
      "targetTotalStake": "10722529369424"
    },
    {
      "votePubkey": "6MP6Bun9VmkGcRVU4iF14Q8P7jTkGtQW9zVwmB9kCYyK",
      "delta": "386896304260",
      "existingStake": "10335633065164",
      "existingActiveStake": "10335633065164",
      "targetStake": {
        "directed": "0",
        "undirectedWhitelist": "10722529369424"
      },
      "targetTotalStake": "10722529369424"
    },
    {
      "votePubkey": "mythxna3hpzXSbaseyR12vu5Vvym1HxS92eCgXLvY7w",
      "delta": "386901190216",
      "existingStake": "10336878770269",
      "existingActiveStake": "10336878770269",
      "targetStake": {
        "directed": "1250591061",
        "undirectedWhitelist": "10722529369424"
      },
      "targetTotalStake": "10723779960485"
    },
    {
      "votePubkey": "3iPuTgpWaaC6jYEY7kd993QBthGsQTK3yPCrNJyPMhCD",
      "delta": "384418894837",
      "existingStake": "10338110474587",
      "existingActiveStake": "10338110474587",
      "targetStake": {
        "directed": "0",
        "undirectedWhitelist": "10722529369424"
      },
      "targetTotalStake": "10722529369424"
    },
    {
      "votePubkey": "EBVj3uwSKZpqEb1K267JaPxDQhULVqCy6hYeQqjsPh81",
      "delta": "513530070511",
      "existingStake": "10208999298913",
      "existingActiveStake": "10208999298913",
      "targetStake": {
        "directed": "0",
        "undirectedWhitelist": "10722529369424"
      },
      "targetTotalStake": "10722529369424"
    },
    {
      "votePubkey": "EdkhvJYa3kWQkFJAPzmGsQyi1D2JA5a7vwWw4hDuwbt",
      "delta": "384401358168",
      "existingStake": "10338128011256",
      "existingActiveStake": "10338128011256",
      "targetStake": {
        "directed": "0",
        "undirectedWhitelist": "10722529369424"
      },
      "targetTotalStake": "10722529369424"
    },
    {
      "votePubkey": "CNcaYdqkCwxDpKSVK8in5f6kqrTiZ5SuHsHFDqx6jNvu",
      "delta": "579685513340",
      "existingStake": "10142870473002",
      "existingActiveStake": "10142870473002",
      "targetStake": {
        "directed": "26616918",
        "undirectedWhitelist": "10722529369424"
      },
      "targetTotalStake": "10722555986342"
    },
    {
      "votePubkey": "5daP6pZoPSak6UEKuRg2HHjvTPpqqwB113oNamGNKuuZ",
      "delta": "488117621759",
      "existingStake": "52158221428327",
      "existingActiveStake": "52158221428327",
      "targetStake": {
        "directed": "41923809680662",
        "undirectedWhitelist": "10722529369424"
      },
      "targetTotalStake": "52646339050086"
    },
    {
      "votePubkey": "nateBZg7oHVPLB2samBLkKvfzedU3ALZBexMFPMKjn1",
      "delta": "582671828110",
      "existingStake": "10140179266065",
      "existingActiveStake": "10140179266065",
      "targetStake": {
        "directed": "321724751",
        "undirectedWhitelist": "10722529369424"
      },
      "targetTotalStake": "10722851094175"
    },
    {
      "votePubkey": "stsaYQJUhKZDHSqndGtgo6jgbhVaHBSHhtfVWxCwrhD",
      "delta": "317009015611",
      "existingStake": "10405520353813",
      "existingActiveStake": "10405520353813",
      "targetStake": {
        "directed": "0",
        "undirectedWhitelist": "10722529369424"
      },
      "targetTotalStake": "10722529369424"
    },
    {
      "votePubkey": "axyQeKp44XqUnvC1jVHoeuAJ3j8wVnGeWtddeAcNYcF",
      "delta": "386902169184",
      "existingStake": "10335627200240",
      "existingActiveStake": "10335627200240",
      "targetStake": {
        "directed": "0",
        "undirectedWhitelist": "10722529369424"
      },
      "targetTotalStake": "10722529369424"
    },
    {
      "votePubkey": "chrtyiAw8suFRvS7rTcfgcDyNu49bGPNZ2fjSPzNPFr",
      "delta": "315818331706",
      "existingStake": "10406711037718",
      "existingActiveStake": "10406711037718",
      "targetStake": {
        "directed": "0",
        "undirectedWhitelist": "10722529369424"
      },
      "targetTotalStake": "10722529369424"
    },
    {
      "votePubkey": "9ymU1ayh9mZVyDL4dUUtXKtX1wCaFNzZPGutLJgqzuC1",
      "delta": "1083779388144",
      "existingStake": "9657319298595",
      "existingActiveStake": "9657319298595",
      "targetStake": {
        "directed": "18569317315",
        "undirectedWhitelist": "10722529369424"
      },
      "targetTotalStake": "10741098686739"
    },
    {
      "votePubkey": "9f7dqiYNBZbgPesAnLeWnKCtxYHSfMg5x1EMZCJwVwG7",
      "delta": "584411156170",
      "existingStake": "10138118213254",
      "existingActiveStake": "10138118213254",
      "targetStake": {
        "directed": "0",
        "undirectedWhitelist": "10722529369424"
      },
      "targetTotalStake": "10722529369424"
    },
    {
      "votePubkey": "4FsAxdHQ6HmFrDD7yCwsKNApuA67QYSCMoLAy3NfySxJ",
      "delta": "390280811307",
      "existingStake": "10338276237002",
      "existingActiveStake": "10338276237002",
      "targetStake": {
        "directed": "6027678885",
        "undirectedWhitelist": "10722529369424"
      },
      "targetTotalStake": "10728557048309"
    },
    {
      "votePubkey": "PineDoC593nrX16W8ZLWfF5Evb6otv7fRfZMLjPAHe3",
      "delta": "315843290264",
      "existingStake": "10406686079160",
      "existingActiveStake": "10406686079160",
      "targetStake": {
        "directed": "0",
        "undirectedWhitelist": "10722529369424"
      },
      "targetTotalStake": "10722529369424"
    },
    {
      "votePubkey": "3Xn3K5zeTzs4sURj1PCRaF6rvFg2hPgT49B4SiM998f7",
      "delta": "578408794575",
      "existingStake": "15117777568789",
      "existingActiveStake": "15117777568789",
      "targetStake": {
        "directed": "4973656993940",
        "undirectedWhitelist": "10722529369424"
      },
      "targetTotalStake": "15696186363364"
    },
    {
      "votePubkey": "76DafWkJ6pGK2hoD41HjrM4xTBhfKqrDYDazv13n5ir1",
      "delta": "1154209992811",
      "existingStake": "9568380843257",
      "existingActiveStake": "9568380843257",
      "targetStake": {
        "directed": "61466644",
        "undirectedWhitelist": "10722529369424"
      },
      "targetTotalStake": "10722590836068"
    },
    {
      "votePubkey": "21wUViiyG1g47VZ39ZZsSkFX9nu6bkyfy6jryHGD2TUB",
      "delta": "384393079215",
      "existingStake": "10338361341445",
      "existingActiveStake": "10338361341445",
      "targetStake": {
        "directed": "225051236",
        "undirectedWhitelist": "10722529369424"
      },
      "targetTotalStake": "10722754420660"
    },
    {
      "votePubkey": "eyeVhGmVEoPSWmQU2wP5WZmMihPBTCk7kMMm4VhuAKS",
      "delta": "384393137506",
      "existingStake": "10338136231918",
      "existingActiveStake": "10338136231918",
      "targetStake": {
        "directed": "0",
        "undirectedWhitelist": "10722529369424"
      },
      "targetTotalStake": "10722529369424"
    },
    {
      "votePubkey": "masvNDXtxVVMrYSV84RMry97JyHXAFcdfTZJ5VzpSYR",
      "delta": "577774739665",
      "existingStake": "10144754629759",
      "existingActiveStake": "10144754629759",
      "targetStake": {
        "directed": "0",
        "undirectedWhitelist": "10722529369424"
      },
      "targetTotalStake": "10722529369424"
    },
    {
      "votePubkey": "tri1cHBy47fPyhCvrCf6FnR7Mz6XdSoSBah2FsZVQeT",
      "delta": "386409512088",
      "existingStake": "10336189198826",
      "existingActiveStake": "10336189198826",
      "targetStake": {
        "directed": "69341489",
        "undirectedWhitelist": "10722529369424"
      },
      "targetTotalStake": "10722598710914"
    },
    {
      "votePubkey": "ACCRENAtboR1MyyoiPvwNZNkjt1GcLARrACh6hZXdddF",
      "delta": "386994326599",
      "existingStake": "10335535042825",
      "existingActiveStake": "10335535042825",
      "targetStake": {
        "directed": "0",
        "undirectedWhitelist": "10722529369424"
      },
      "targetTotalStake": "10722529369424"
    },
    {
      "votePubkey": "gVot34jauJpexBL2YUSPBKsmZ4V2ffmDcRk4yfSEnx8",
      "delta": "476903219442",
      "existingStake": "10255326943817",
      "existingActiveStake": "9280349063788",
      "targetStake": {
        "directed": "9700793835",
        "undirectedWhitelist": "10722529369424"
      },
      "targetTotalStake": "10732230163259"
    },
    {
      "votePubkey": "CHiaohVV2SQCFhiYP73iQzWT6HxnZqnAZJJqAYTeLAo",
      "delta": "317059069676",
      "existingStake": "10405470299748",
      "existingActiveStake": "10405470299748",
      "targetStake": {
        "directed": "0",
        "undirectedWhitelist": "10722529369424"
      },
      "targetTotalStake": "10722529369424"
    },
    {
      "votePubkey": "nebu1WnZBrFZz5X7sfPWuEqyb8LBSsrXpxaesnK9CRE",
      "delta": "315818241767",
      "existingStake": "10406711127657",
      "existingActiveStake": "10406711127657",
      "targetStake": {
        "directed": "0",
        "undirectedWhitelist": "10722529369424"
      },
      "targetTotalStake": "10722529369424"
    },
    {
      "votePubkey": "EMVmh5hF6LT1sZM9G7dEX1bykRYEymWY2vtE7QHBBAW6",
      "delta": "384393646047",
      "existingStake": "10338135723377",
      "existingActiveStake": "10338135723377",
      "targetStake": {
        "directed": "0",
        "undirectedWhitelist": "10722529369424"
      },
      "targetTotalStake": "10722529369424"
    },
    {
      "votePubkey": "HMV14UAuULSwqmZhsKHzaVkYAd94iWpEeURgbUegfQLc",
      "delta": "315819444104",
      "existingStake": "10406709925320",
      "existingActiveStake": "10406709925320",
      "targetStake": {
        "directed": "0",
        "undirectedWhitelist": "10722529369424"
      },
      "targetTotalStake": "10722529369424"
    },
    {
      "votePubkey": "ELE2xaC6i6pmeu7bfrYjBv4whBeTAbgwcg5hf2ythiBs",
      "delta": "490865426140",
      "existingStake": "10239056302735",
      "existingActiveStake": "10239056302735",
      "targetStake": {
        "directed": "7392359451",
        "undirectedWhitelist": "10722529369424"
      },
      "targetTotalStake": "10729921728875"
    },
    {
      "votePubkey": "NeodymeDFipD7eA1ShrLJAZTBdHWcFsDB9YkoHshZNk",
      "delta": "386950394472",
      "existingStake": "10335578974952",
      "existingActiveStake": "10335578974952",
      "targetStake": {
        "directed": "0",
        "undirectedWhitelist": "10722529369424"
      },
      "targetTotalStake": "10722529369424"
    },
    {
      "votePubkey": "6oscGUEkXE8fyWoC4czRKbM1cuLkJNtgRsX1Un6w88Vf",
      "delta": "582670164398",
      "existingStake": "10139859205026",
      "existingActiveStake": "10139859205026",
      "targetStake": {
        "directed": "0",
        "undirectedWhitelist": "10722529369424"
      },
      "targetTotalStake": "10722529369424"
    },
    {
      "votePubkey": "GNZ1PAAS33davY4Q1BMEpZEpVBtRtGvSpcTH5wYVkkVt",
      "delta": "6181956892",
      "existingStake": "10716347412532",
      "existingActiveStake": "7844748098434",
      "targetStake": {
        "directed": "0",
        "undirectedWhitelist": "10722529369424"
      },
      "targetTotalStake": "10722529369424"
    },
    {
      "votePubkey": "AY271jdvcyo5VzBiWsMGLEjpZFFrarq8FDydJHLmYgCG",
      "delta": "384393013613",
      "existingStake": "10338136355811",
      "existingActiveStake": "10338136355811",
      "targetStake": {
        "directed": "0",
        "undirectedWhitelist": "10722529369424"
      },
      "targetTotalStake": "10722529369424"
    },
    {
      "votePubkey": "FCvNkHa4U3yh7AXWGGL2jWLWiSRouR8EtzY5WVTHKTHa",
      "delta": "317006745612",
      "existingStake": "10405522623812",
      "existingActiveStake": "10405522623812",
      "targetStake": {
        "directed": "0",
        "undirectedWhitelist": "10722529369424"
      },
      "targetTotalStake": "10722529369424"
    },
    {
      "votePubkey": "1KXz4xKV2viJCGpxqnQqdf2J45vQr5USdmtcJLTaHkm",
      "delta": "384393166766",
      "existingStake": "10338136202658",
      "existingActiveStake": "10338136202658",
      "targetStake": {
        "directed": "0",
        "undirectedWhitelist": "10722529369424"
      },
      "targetTotalStake": "10722529369424"
    },
    {
      "votePubkey": "fuyugZxM5S4NyV3ZYoc6ebs3fmRTrZ3X27MKCFvHpVD",
      "delta": "384393593690",
      "existingStake": "10338135775734",
      "existingActiveStake": "10338135775734",
      "targetStake": {
        "directed": "0",
        "undirectedWhitelist": "10722529369424"
      },
      "targetTotalStake": "10722529369424"
    },
    {
      "votePubkey": "91413b9eEvG6UofpSgwdUgH9Lz4QBF1G3J325Bw7JwGR",
      "delta": "576971957490",
      "existingStake": "10146967811556",
      "existingActiveStake": "10146967811556",
      "targetStake": {
        "directed": "1410399622",
        "undirectedWhitelist": "10722529369424"
      },
      "targetTotalStake": "10723939769046"
    },
    {
      "votePubkey": "TKMA1fBGq4M7gF2CNnhphX6vNateFc2cm2FL2mYwq7e",
      "delta": "384408136463",
      "existingStake": "10338121232961",
      "existingActiveStake": "10338121232961",
      "targetStake": {
        "directed": "0",
        "undirectedWhitelist": "10722529369424"
      },
      "targetTotalStake": "10722529369424"
    },
    {
      "votePubkey": "LunarE7WQyxpPwKo2hkEZZquu6UDWMNjvf3JyzGmdfp",
      "delta": "563912956229",
      "existingStake": "10158616413195",
      "existingActiveStake": "10158616413195",
      "targetStake": {
        "directed": "0",
        "undirectedWhitelist": "10722529369424"
      },
      "targetTotalStake": "10722529369424"
    },
    {
      "votePubkey": "metaRWEc85haGPz6P79kiuG3F8JXKjR7oQr2zjokUCU",
      "delta": "386991624463",
      "existingStake": "10335537744961",
      "existingActiveStake": "10335537744961",
      "targetStake": {
        "directed": "0",
        "undirectedWhitelist": "10722529369424"
      },
      "targetTotalStake": "10722529369424"
    },
    {
      "votePubkey": "bookLxG3LkSmt4htJ1x9zPw6E34RRMAi7sUn5mM3CNN",
      "delta": "598370601730",
      "existingStake": "12152979160171",
      "existingActiveStake": "12152979160171",
      "targetStake": {
        "directed": "2028820392477",
        "undirectedWhitelist": "10722529369424"
      },
      "targetTotalStake": "12751349761901"
    },
    {
      "votePubkey": "burnn86ebxJnhtk3cfpHoZxy5nUaC3K9U8VwzgqhEEt",
      "delta": "387298068410",
      "existingStake": "10356762845654",
      "existingActiveStake": "10356762845654",
      "targetStake": {
        "directed": "21531544640",
        "undirectedWhitelist": "10722529369424"
      },
      "targetTotalStake": "10744060914064"
    },
    {
      "votePubkey": "BANX7gZwUYFiFJKX9i2hHygy6DxixPutQoQW1U1oBdwt",
      "delta": "236144847685",
      "existingStake": "14244540310344",
      "existingActiveStake": "14244540310344",
      "targetStake": {
        "directed": "3758155788605",
        "undirectedWhitelist": "10722529369424"
      },
      "targetTotalStake": "14480685158029"
    },
    {
      "votePubkey": "THWfRpcJSC7oDrNMSCcixTZmCHVBTEVQL4qnd1UTD1x",
      "delta": "647603660244",
      "existingStake": "24416023308379",
      "existingActiveStake": "24416023308379",
      "targetStake": {
        "directed": "14341097599199",
        "undirectedWhitelist": "10722529369424"
      },
      "targetTotalStake": "25063626968623"
    },
    {
      "votePubkey": "HMk1qny4fvMnajErxjXG5kT89JKV4cx1PKa9zhQBF9ib",
      "delta": "584582842327",
      "existingStake": "10580310974667",
      "existingActiveStake": "10580310974667",
      "targetStake": {
        "directed": "442364447569",
        "undirectedWhitelist": "10722529369424"
      },
      "targetTotalStake": "11164893816994"
    },
    {
      "votePubkey": "56CV9agH7K12coC6aiTqgprWcbxihGu1GCw6mwd34YhQ",
      "delta": "584411666033",
      "existingStake": "10138117703391",
      "existingActiveStake": "10138117703391",
      "targetStake": {
        "directed": "0",
        "undirectedWhitelist": "10722529369424"
      },
      "targetTotalStake": "10722529369424"
    },
    {
      "votePubkey": "6q1VNp8Vy2Go12vb8CwbjUqqj2SXr2JYftJRWs71sW23",
      "delta": "-2282200",
      "existingStake": "6813627600747",
      "existingActiveStake": "4492204826472",
      "targetStake": {
        "directed": "6813625318547",
        "undirectedWhitelist": "0"
      },
      "targetTotalStake": "6813625318547"
    },
    {
      "votePubkey": "DriFTm3wM9ugxhCA1K3wVQMSdC4Dv4LNmyZMmZiuHRpp",
      "delta": "-43272432452",
      "existingStake": "55037478154",
      "existingActiveStake": "55037478154",
      "targetStake": {
        "directed": "11765045702",
        "undirectedWhitelist": "0"
      },
      "targetTotalStake": "11765045702"
    },
    {
      "votePubkey": "juicQdAnksqZ5Yb8NQwCLjLWhykvXGktxnQCDvMe6Nx",
      "delta": "-439146585",
      "existingStake": "25682493958",
      "existingActiveStake": "25682493958",
      "targetStake": {
        "directed": "25243347373",
        "undirectedWhitelist": "0"
      },
      "targetTotalStake": "25243347373"
    },
    {
      "votePubkey": "CogentC52e7kktFfWHwsqSmr8LiS1yAtfqhHcftCPcBJ",
      "delta": "-11054680964916",
      "existingStake": "13844726466599",
      "existingActiveStake": "13844726466599",
      "targetStake": {
        "directed": "2790045501683",
        "undirectedWhitelist": "0"
      },
      "targetTotalStake": "2790045501683"
    },
    {
      "votePubkey": "B6nDYYLc2iwYqY3zdmavMmU9GjUL2hf79MkufviM2bXv",
      "delta": "-4641538",
      "existingStake": "13868930223",
      "existingActiveStake": "13868930223",
      "targetStake": {
        "directed": "13864288685",
        "undirectedWhitelist": "0"
      },
      "targetTotalStake": "13864288685"
    },
    {
      "votePubkey": "sw222BfVDABppvydacSCj3JVaPSC83RoRtyvLmr6pNx",
      "delta": "76001",
      "existingStake": "60116278",
      "existingActiveStake": "60116278",
      "targetStake": {
        "directed": "60192279",
        "undirectedWhitelist": "0"
      },
      "targetTotalStake": "60192279"
    },
    {
      "votePubkey": "EpicsoqLdDP8qRn3wQRKTSKAXbjK9dUgFfNPRQS77MQD",
      "delta": "9",
      "existingStake": "12221519",
      "existingActiveStake": "12221519",
      "targetStake": {
        "directed": "12221528",
        "undirectedWhitelist": "0"
      },
      "targetTotalStake": "12221528"
    },
    {
      "votePubkey": "EsSodfiCfuM4ANfpPAunwj3wo8RaoRrZR9yY79CoXoUV",
      "delta": "-3285728",
      "existingStake": "3285728",
      "existingActiveStake": "3285728",
      "targetStake": {
        "directed": "0",
        "undirectedWhitelist": "0"
      },
      "targetTotalStake": "0"
    },
    {
      "votePubkey": "4565LXcdfFzN9bHqo1eCZRogsgQREf4oiyjoKuWu7XTX",
      "delta": "-3285728",
      "existingStake": "3285728",
      "existingActiveStake": "3285728",
      "targetStake": {
        "directed": "0",
        "undirectedWhitelist": "0"
      },
      "targetTotalStake": "0"
    },
    {
      "votePubkey": "ChaosDKeBjU22B4nnvYWXyTRPuWTzJBR4m3QPfBw6Tta",
      "delta": "-10337252978248",
      "existingStake": "10337252978248",
      "existingActiveStake": "10337252978248",
      "targetStake": {
        "directed": "0",
        "undirectedWhitelist": "0"
      },
      "targetTotalStake": "0"
    },
    {
      "votePubkey": "Luck3DN3HhkV6oc7rPQ1hYGgU3b5AhdKW9o1ob6AyU9",
      "delta": "-7486063168238",
      "existingStake": "7486063168238",
      "existingActiveStake": "7486063168238",
      "targetStake": {
        "directed": "0",
        "undirectedWhitelist": "0"
      },
      "targetTotalStake": "0"
    },
    {
      "votePubkey": "Hx4UJCvf8amGeuW9fPFfTckRoznDHxPSYiU9HuUSZKLT",
      "delta": "7319537395",
      "existingStake": "3285729",
      "existingActiveStake": "3285729",
      "targetStake": {
        "directed": "7322823124",
        "undirectedWhitelist": "0"
      },
      "targetTotalStake": "7322823124"
    },
    {
      "votePubkey": "EARNynHRWg6GfyJCmrrizcZxARB3HVzcaasvNa8kBS72",
      "delta": "1157198865236",
      "existingStake": "8357688517263",
      "existingActiveStake": "8357688517263",
      "targetStake": {
        "directed": "9514887382499",
        "undirectedWhitelist": "0"
      },
      "targetTotalStake": "9514887382499"
    },
    {
      "votePubkey": "SoLiDDVm88uWUMk2rQpG7B9wC55a6xveYEz3JnS6tzC",
      "delta": "177457228356",
      "existingStake": "3282880",
      "existingActiveStake": "3282880",
      "targetStake": {
        "directed": "177460511236",
        "undirectedWhitelist": "0"
      },
      "targetTotalStake": "177460511236"
    },
    {
      "votePubkey": "GREEDkpTvpKzcGvBu9qd36yk6BfjTWPShB67gLWuixMv",
      "delta": "-10143750722442",
      "existingStake": "10143750722442",
      "existingActiveStake": "10143750722442",
      "targetStake": {
        "directed": "0",
        "undirectedWhitelist": "0"
      },
      "targetTotalStake": "0"
    },
    {
      "votePubkey": "steakxfubt37xYdvuXz7BV5Uhhhk1FyJx9zGHfDcTVr",
      "delta": "-10338136106197",
      "existingStake": "10338136106197",
      "existingActiveStake": "10338136106197",
      "targetStake": {
        "directed": "0",
        "undirectedWhitelist": "0"
      },
      "targetTotalStake": "0"
    },
    {
      "votePubkey": "mintrNtxN3PhAB45Pt41XqyKghTTpqcoBkQTZqh96iR",
      "delta": "1170089539",
      "existingStake": "3285728",
      "existingActiveStake": "3285728",
      "targetStake": {
        "directed": "1173375267",
        "undirectedWhitelist": "0"
      },
      "targetTotalStake": "1173375267"
    },
    {
      "votePubkey": "AZUYzQX7nrbN1iE25YsSCSZAywZcyr1C1anMnwZtaqX9",
      "delta": "-2282655",
      "existingStake": "2248019008971",
      "existingActiveStake": "3285506",
      "targetStake": {
        "directed": "2248016726316",
        "undirectedWhitelist": "0"
      },
      "targetTotalStake": "2248016726316"
    }
  ],
  "actualIncreases": [],
  "actualDecreases": [],
  "actualAdds": [],
  "actualRemovals": [],
  "directedStakeTargets": [
    {
      "votePubkey": "6q1VNp8Vy2Go12vb8CwbjUqqj2SXr2JYftJRWs71sW23",
      "sum": "6813625318547.11189735",
      "wallets": [
        {
          "adress": "HFppr7mxYuNCCPvLAuvSuoThoxdenzJa9gGPdebZnyXt",
          "amount": "250945142.66149735"
        },
        {
          "adress": "AqYhUPiHQ45SAuVDRNBC41egAQd1T6r5vFdiE9X5vRg4",
          "amount": "4863080062437.864"
        },
        {
          "adress": "6Lj7eUvRomwkDtWpGmwhrySpKnXz6xYYN7EZKy3Tq3M3",
          "amount": "1950294310966.5864"
        }
      ]
    },
    {
      "votePubkey": "7K8DVxtNJGnMtUY1CQJT5jcs8sFGSZTDiG7kowvFpECh",
      "sum": "785292645457.62338918850432",
      "wallets": [
        {
          "adress": "7dby9hdizvjPsL4tNEatbhtJiitQysW3iC2wpcCXauQS",
          "amount": "9968305.40197518"
        },
        {
          "adress": "ERxi9mUDYS1Jw4dRheLEQ3G7pRUcGXevSx17Wwmk8hhW",
          "amount": "16169940.53782699"
        },
        {
          "adress": "Fexu4NMQ8hLedDJSoiHH37WhusCKbkKfqrFxtUniUxV",
          "amount": "2039934497.629079"
        },
        {
          "adress": "HCXcmiM4oNLR9GD4ozs5WqKg389pJfzkdUYS6RixTKHk",
          "amount": "3511.3148041113323"
        },
        {
          "adress": "9fRmJJm2Z4bMvgyuLvUsQbPXSTxFGPchUUdFEiFxQnVh",
          "amount": "74342.82197835096"
        },
        {
          "adress": "6jeNzFGvGjEmvrVrjHwR93XvPTnSg8LKMuWtfngWFNkr",
          "amount": "53011567.09584764"
        },
        {
          "adress": "7P45T3FJNwNKjfa2LnD3yFerP1Tov4ycJdUCeJr4RskV",
          "amount": "1065626934.0205824"
        },
        {
          "adress": "Etk1W3L51AfRHtwzvHqnVUg5SGW4kDE7MZ7W3QnwBTPu",
          "amount": "272617609.01485497"
        },
        {
          "adress": "ALULiprxCdFEjbhYzhmyLzwjHCaMWXPHuStXMsh73fkW",
          "amount": "0"
        },
        {
          "adress": "BBzwtu47gPEjpCyLpcWCRkFPi3PqqQ9nG3Dhhopvfq7x",
          "amount": "27397278.02445635"
        },
        {
          "adress": "7cZx76kp6jBfq2mYqLN43ynAC3Zw9PVtnbUmMFhGtfEe",
          "amount": "10612100131.801197"
        },
        {
          "adress": "HFUex3SnvL8QvXFZq2tkxm529xxofNzgAiPvaXx1zCNS",
          "amount": "2511936578.2055807"
        },
        {
          "adress": "GG5FWwCWWxS3HdkJuv57mZLrVMyWPmx5vSteMMDLfnva",
          "amount": "17516529.76520369"
        },
        {
          "adress": "5HNJRXLGpCy6hRVvXcmsUmBQK6duQBhnrGSLfFXSLNVd",
          "amount": "371888069.369008"
        },
        {
          "adress": "DzSngdJXHdWGmUUGC7nhLgk7kv538tHE5ZRV88mLJbbB",
          "amount": "20851413461.214096"
        },
        {
          "adress": "FX2bhFo9ykqRDCXcgyXjNkL7Y7N8qRKsWoHq5YpQXLiA",
          "amount": "461446987.5805309"
        },
        {
          "adress": "Haj2mRsA8ay1J7FgwspAdvCYmqVJExMZqqLY7Vnmj4XB",
          "amount": "986639.1125491501"
        },
        {
          "adress": "757omZMDbkC1aQE6jGPVyph5dK5iq9wTuZJK4Fkz1zye",
          "amount": "21331621654.601196"
        },
        {
          "adress": "7TJW67iR4epVp9U5VPrW7iF68Td1jDnBpE8KyifLNnoy",
          "amount": "38396919204.66382"
        },
        {
          "adress": "HqN2m3a6s7dVYy136aksVnGzqWq34cH5xPmgcNCrH3qU",
          "amount": "33085917.700720545"
        },
        {
          "adress": "FjdLRYTamMpzFsYd3xEiUKkJJLger5p7PEVZkPCRuQTR",
          "amount": "364669691.5937492"
        },
        {
          "adress": "5uc4ebLBtwtJA3gskpT125f4g7DAFYTbF1k2t534sxR4",
          "amount": "1090470436.0594199"
        },
        {
          "adress": "6LsscaTrb5E18UAxVzRGM3AyTS9ERw6LiJB2KDxq23hD",
          "amount": "52958212635.77552"
        },
        {
          "adress": "A8LcRg1XfDYDrNtdgyLKBeFF18GiXE4q27dPpEjRZ8xL",
          "amount": "2026305270.3315175"
        },
        {
          "adress": "2R8SXghkGLjwAR2LzT2X5S7AFuhpUufLX1BzA4eMS7hb",
          "amount": "1090470436.0594199"
        },
        {
          "adress": "4c6Scmh1paCPomnn76A2j8qSekqpYXCngMxpixgcEsL1",
          "amount": "1099558606.415395"
        },
        {
          "adress": "FBtd2XJuQwvN6KjWJqKcvmaUCG8UvUCwQ4KXEiXE4PTL",
          "amount": "24901744.064827416"
        },
        {
          "adress": "9JipXtoAV7iHR4djmjeM6zDey8S6PQX5VJ57G85DWreo",
          "amount": "1449363857.772663"
        },
        {
          "adress": "EGqd9xryXUJA1a9swJpdS8PtWMzMUA51XwFYSSE57GFS",
          "amount": "3465524466.3709335"
        },
        {
          "adress": "8UBzieevdAcd8VVGtQEDKNT9arFjHSdM1LPTPjRDrKoh",
          "amount": "5314363494.087748"
        },
        {
          "adress": "7PrHNVreQJepjiNcnv3jEhhS8VuqjoLxYDQfDy9Kdd1K",
          "amount": "2305.2545018296137"
        },
        {
          "adress": "Br3P85TGSytYwoXtNUPPhzJvUj69UesoDVrzDMy3q8j8",
          "amount": "1498585300.7642488"
        },
        {
          "adress": "DAmwnCazFkum3dK9gf3Dct5FoVfWjnZDLAeDRtmUFeRw",
          "amount": "53011723.03311999"
        },
        {
          "adress": "3dt8pSCQxKf8Mdhpr17K1x9HRQaDm6QUfga8ttV82xmc",
          "amount": "9.81423392453478"
        },
        {
          "adress": "9LTJU26ra4f75EGtMswyYE56L6h1zGW4MUeFBAN5Wehv",
          "amount": "29497625.498057343"
        },
        {
          "adress": "3VeuudVhqxq1xFCnKFWNEArJDLiH6WZJh2JiUorUrHS1",
          "amount": "51254642.567145266"
        },
        {
          "adress": "ChJaUaPDNm9SyL16c3TFtzxfTaS1ziwDFDbsfjHd3D4T",
          "amount": "4265026.160106882"
        },
        {
          "adress": "GXzbgMeBVY2qDQ2Joz7PrJmXsd5ZN5y7Rz5VqZobXsW9",
          "amount": "7970.2484171583"
        },
        {
          "adress": "EMtTEqPjMbo4aBorhauonT1sZLa94dyRtdCwtTPqqjTy",
          "amount": "2.18094087211884"
        },
        {
          "adress": "Dwmm4sLERvchzNCWKNSYtbEjw69Ks5NgXfECHf87faCn",
          "amount": "6666130.832325247"
        },
        {
          "adress": "2jX6YfmYF1gEdN7zRW3Gpw4e75BpBexNVVk28eQkKhzU",
          "amount": "24029737.385457706"
        },
        {
          "adress": "6csJHaV2xPLASFK7YV9cqP411Vkh8MN7mxo4bD4UydbA",
          "amount": "8325129837.838127"
        },
        {
          "adress": "HXrTymzMrFRQFFrexaDjcakEgEfs88EJvKaA44jacpgT",
          "amount": "1499259182.0510316"
        },
        {
          "adress": "6Yjh1ph5aeeyvSncnykAGEC5WPhqbfs92pHfTrGPc5n4",
          "amount": "10119100897.945803"
        },
        {
          "adress": "4KRpjr88WMHGgYjppMpKDrbLeoCMqEKBomJFUh5gJWkk",
          "amount": "389490671.0562003"
        },
        {
          "adress": "GKQLTBev3jUUkZPuAF24QksffLcS7J3AaPF3hmnEvoTk",
          "amount": "6061242712.57461"
        },
        {
          "adress": "gKbCsvZ8EtnCFa9Grf4q3AAPse2PvcZ9kbvd1bbhTmh",
          "amount": "1567630.8561772485"
        },
        {
          "adress": "7zV7mKKihBcobobibYT4jYxF41ebTj8LD4vjhCdXFdqM",
          "amount": "1066581082.5664892"
        },
        {
          "adress": "8KTUbV95TvuJLVgZhmqNapQKE6XYBuKEo9hspExCU3C6",
          "amount": "7756780453.39625"
        },
        {
          "adress": "3THkFN9tz3AhQ3MM8aKo7ezYkmLq749CfKFGSSZGRBhE",
          "amount": "313456113.96228504"
        },
        {
          "adress": "6dZmpoVdHiGHkdgKJ7YJko2SoqnK89n1C6FtroJJePGJ",
          "amount": "2826.4993702660167"
        },
        {
          "adress": "3dSEUd3urnFtxZSciiL5Lne4cF9NeUwD34ssaKSAtUHY",
          "amount": "10675152.70051064"
        },
        {
          "adress": "5dVBJoAAbGjuxx1jea5tqo6HjWvsKfE1q7EvvxeHDBj3",
          "amount": "2187342193.1104727"
        },
        {
          "adress": "95rEJcYce9Dhsy6jtE838NenmD5SkzpEuaSjGT6Y9Uru",
          "amount": "5671136430.609847"
        },
        {
          "adress": "2BUxhYFpUa9MM3ZcR3mG41ko9GPgxrGMFSM7pHA7SeNH",
          "amount": "1688329697.4347038"
        },
        {
          "adress": "4vtaX6qkX512ChRWC6tegieEHKiL7NmkoH6QJYr3JXp9",
          "amount": "184748359.47742012"
        },
        {
          "adress": "4pwiLy7f8mBj5hDmmm3va4PkiBCeQem2y8ot3aDrHBvw",
          "amount": "1959339102.459867"
        },
        {
          "adress": "J4AnDQ4L6XQ2vsFVrqn5BBe8c8pMrvDLTEUyi9mWHvBM",
          "amount": "10259344.328066386"
        },
        {
          "adress": "5DM6Wa9fiAfvUGLCegvdcTjVW1rtTwu4Fjpp71onYxyq",
          "amount": "4380.41974165069"
        },
        {
          "adress": "5wPjGpUPm6uQc5UEgjPmrgZLsqfCFaVdrhFHG1uvNE5m",
          "amount": "5338240267.913729"
        },
        {
          "adress": "4QTR6bYfMiEegxUFuVo3XeasK4PjQW5CkWYi1qKQSMC8",
          "amount": "21338502.149021372"
        },
        {
          "adress": "xQWm4PfSDShcfPHJvtCAdD6LaQpbzzPW4AadEPanP6Z",
          "amount": "53011488.58197624"
        },
        {
          "adress": "C8ABSEJtRVzZi8kzb14SXqfGXZR1A6aX43bGk2A38nXr",
          "amount": "2538407.9857634786"
        },
        {
          "adress": "DV4xEyvG892xofioLxryAyhjYua6RFHxtuo95n5xQMSv",
          "amount": "608364865.5514551"
        },
        {
          "adress": "7B5apUY2Du5i5BF2u37Pxwseb1kQB3nbbFu5xYHnHdwM",
          "amount": "109.047043605942"
        },
        {
          "adress": "DoMavGEK9By86vRghPaKij8ztiLefdM3jH9EMMCycGvn",
          "amount": "656035.7380968356"
        },
        {
          "adress": "DddLmKCaVhAiiJQUhSZqP9RJfLVqggprnzAmeVFGBJ76",
          "amount": "2556944.8927060524"
        },
        {
          "adress": "D2VorVhYKxDNVuQKYk8rBu1iaDxbDjArwEJg6puFxHhi",
          "amount": "1199657144.9378715"
        },
        {
          "adress": "8526uPCepabV5ZkZKBFrw3AAHJ3RHZ9bUpM6bGjHPNoq",
          "amount": "1143716151.1482391"
        },
        {
          "adress": "CU65rCkqctQiV8yCTB8FtxADqG9Ez5oxLwi84vnm1wVk",
          "amount": "9391475643.774744"
        },
        {
          "adress": "3W19eEuBr44b2xdECKpBagDzXsktjMZ2qk2YL16oXDCU",
          "amount": "1107909438.828972"
        },
        {
          "adress": "F5YhPtiivx294rxze6f9SdQnbsLR2NZsMZbLxREmU5wK",
          "amount": "6418552480.059088"
        },
        {
          "adress": "A4CnU6zcCCH8Wne8n6QF7QfLEizrGHQ7NyYg5pfWMJQt",
          "amount": "10457500.253825359"
        },
        {
          "adress": "9BvGpvoDxkUJhsYHeYYjqwznXayad4tiapzYjQz1fgrG",
          "amount": "514627303.8858883"
        },
        {
          "adress": "6imxdjaNVK94ncNmn2bfNAeUk8Gh1GS48yyg7PEkaNDr",
          "amount": "7923482.502037456"
        },
        {
          "adress": "ACcUyJtY2be53TZgNFua4fFXWpUWGepizLfVmPjXwM9d",
          "amount": "100964171965.9207"
        },
        {
          "adress": "2tSziuyyyWHpNeLbnhaJMm6mKC96kvmuwpTywMg968Co",
          "amount": "225517544.3097003"
        },
        {
          "adress": "FxMCSqGBSVY4FEhEHxGGiypH1ZDE7MwbxgdZoTsAXkAc",
          "amount": "117271365.09187953"
        },
        {
          "adress": "wNS2ZZ9nJH25mEWxSvx8eXeTeQJWZbjf3L3w2pkfRkg",
          "amount": "108693.73118465874"
        },
        {
          "adress": "EuqeUDmw97MnHe7mqA3ZEAsjrUZ84dBKSLKM79B2rn5t",
          "amount": "53011619.438428566"
        },
        {
          "adress": "Ap1PS4pPjbbSc1bKG6Ujv5AJsq5vEHJPuok4w7kPuc9g",
          "amount": "2922820395.974824"
        },
        {
          "adress": "Fp3ckgTBtEZ8qe4esvioTbEgnjbnEtDhVaTX1ewAsBMk",
          "amount": "53011408.97763441"
        },
        {
          "adress": "AifAT6xg46py5bjERHHGGixvfUmVMcCWuCMF4HsLtMa8",
          "amount": "9607708915.15854"
        },
        {
          "adress": "GxcRoM1hMXZB8uZ2tXiNA8KwEsEUWcN7WevW31DTvNyM",
          "amount": "1480538740.2103052"
        },
        {
          "adress": "4p7Uca2koD1aVpn4T1bwPc2bcXqCVhvtaLGdVaTnzLSL",
          "amount": "3138725253.6488047"
        },
        {
          "adress": "48NZ8M8X7LzgrHVCnGnDpBETjEFS9v4R8nkg6AFqVjYL",
          "amount": "15221955545.647516"
        },
        {
          "adress": "8nNikttkGXWn1LeTBNkb89HLRzEadxd8CqE3HZo6NuBK",
          "amount": "53011671.781009495"
        },
        {
          "adress": "FrAwojuozHjSLN4kJEnmjha968tyBbMPp2nemts1pi5e",
          "amount": "11240901.8483835"
        },
        {
          "adress": "CqNCMS9jhphPPnnDTRpdqr3pWU6pBJKrXRSME7rGXyd4",
          "amount": "4362332255.7412815"
        },
        {
          "adress": "2XbThfLg4uSUqGAXsPNdyXKJiEvMbGnrorbvUXN4da81",
          "amount": "1744468719.5650542"
        },
        {
          "adress": "6BphC6hVT9M35WaexozJvr6GUCdPbjh6H77tPXqQJxCz",
          "amount": "18357601.979243267"
        },
        {
          "adress": "5ecay8qayyK8k7erYRWdbBoc36yYGP9NXJu1u3MtMMo6",
          "amount": "588991419.4804442"
        },
        {
          "adress": "FaVQ32buKWphZpSV3o2qtMhzs21A4HqnzAFBxi7nEBeZ",
          "amount": "3572951704.4722147"
        },
        {
          "adress": "4gAcUCyxE8HtDzh2VTN829EKEdeHeDc3K5hbHfCEVqFb",
          "amount": "1262729766.308163"
        },
        {
          "adress": "Fgio9obrG3gTe8BUfUozQSMtBivPwxqGQWsXj14yG6ne",
          "amount": "7615989.467536549"
        },
        {
          "adress": "FTBs7jEamdquJbDcENfiJJSbHbCfT4dZauubbfyWpmKL",
          "amount": "21960262.220371988"
        },
        {
          "adress": "G9GmkKh6eb6eWhHKZ4ugnEMmJSZ9GYSbD4xLuUSbX1G1",
          "amount": "52656768960.937836"
        },
        {
          "adress": "Gv27NutHSZsT4ce1biwjLk3m7yomWt9xf5yFUCfRUxQ9",
          "amount": "3868038336.870326"
        },
        {
          "adress": "CL4RGfJxDLjTifyEKGLRKVqmENPGWacSwe2X58LeXmJo",
          "amount": "6251136144.930031"
        },
        {
          "adress": "6rgYLy7Pi2owHga6SXz4nmKAgXiSksEK3AhQ4GB4MRwA",
          "amount": "518716042.41436094"
        },
        {
          "adress": "EnntqBUfPYUPafpEzQyr9E8quUVD2LN8vC7ZYSjBJGPg",
          "amount": "480381888.9705057"
        },
        {
          "adress": "3rqhsBzyTjJA589iaF9SwLbQxpkpFkEaEVrvHUojSjnj",
          "amount": "171203861586.61722"
        },
        {
          "adress": "ADoXBXFgCkN6yZHqdYUcB7GaNcr3WQZaJmo6iZS5GYPe",
          "amount": "51122.34451290167"
        },
        {
          "adress": "2NJM5ec8De4WDsiiDSKbxHfV6M45CLiRrvNfyh4Ec8sA",
          "amount": "123321196.92879795"
        },
        {
          "adress": "BmPn6zoLcQGsXdonqmq8yXaJAvuGetw7pmpSLScm7Kri",
          "amount": "1090470444.7831833"
        },
        {
          "adress": "EijiSSeEdQYbmJoTiVwrcXtLY6jVhnYAcUYG7CtWd7Mi",
          "amount": "21596754.990982015"
        },
        {
          "adress": "3HZfdStM6zcrUsBEw7mBwCPY4y2y8W6TU6fo8swEnhgg",
          "amount": "272617609.01485497"
        },
        {
          "adress": "7wYK2PJb8rtP5PS4BJFVLNTQ3VxSTxw4pyFyY64AZWbn",
          "amount": "76344377879.32309"
        },
        {
          "adress": "B2WoczGQTMzLCNjSrTaNPCWPPpD5m7vTSzu1hWnjJog2",
          "amount": "11246132838.336687"
        },
        {
          "adress": "9wBF2922j7vpSKfqr9Arsybi1zWVF7GY3ZTs6QLjfzEB",
          "amount": "323968190.08049434"
        },
        {
          "adress": "CQ3K1UoqFYa2tyAXitvgdrxBvtV5y3K8zs1Avim41ZCf",
          "amount": "18155896788.128063"
        },
        {
          "adress": "8yThTQiaGVH7ssZDeac7WCYN3fXwUUCCVg6nJxA25TbN",
          "amount": "17176523348.147455"
        },
        {
          "adress": "8XLGrfdktr41h9jCkkfLnSiU9r2sBcyEAQ2LxeDvFixB",
          "amount": "5175074110.00885"
        },
        {
          "adress": "9cGjgK4N1L9qpy15M72cZJJx2XTpU3HVRVuKtGm3WkWh",
          "amount": "2181898192.843245"
        },
        {
          "adress": "84qC44vpro19MNpnB7ag9TubP1PnS1FvpmexyCHLUQDR",
          "amount": "5797897588.500244"
        },
        {
          "adress": "818m2i2cjykgjEN9CVywTsKP1xo78kA2pse64ZGgExDR",
          "amount": "836571885.078308"
        },
        {
          "adress": "2aVe5AQvDkE7HR5RP9cWCUMFQ3yeYSnM8kPZSMPMtpA2",
          "amount": "1086852.2551525747"
        },
        {
          "adress": "B2QowgG5BNohamCrDVwHVmVs7GghdUuh9ikGvSvGJPBs",
          "amount": "65461902.07157158"
        },
        {
          "adress": "DiNA3QPvf1pnJK8DvtBo2AGY9HXA4kA5omz9jNtJjkK3",
          "amount": "4814308080.120225"
        },
        {
          "adress": "6LpQvYaD5ofZdvMuXhqj2MQFCMDyxpyv5DRtaqc1UQtZ",
          "amount": "1080669214.7185986"
        },
        {
          "adress": "7NLq8AvLWK8EWffVYwS4Q9uUgpKjMryUcYaoojvaxMRX",
          "amount": "3193229652.9622087"
        },
        {
          "adress": "4iWj26WUozWKPGDUGgSvnhFk2sme6N9d21Mw9b9Fxfzu",
          "amount": "7169.843117090686"
        },
        {
          "adress": "Es7i4Dm6X4rJ76Dv7G2VrezHHCs8bPEnxzw6dN6qYryY",
          "amount": "1609553610.4269004"
        },
        {
          "adress": "3reBwRgdx7ZLSB1j3mGctWrHCJqAaZMytQms77xnn4iX",
          "amount": "53011775.37570092"
        },
        {
          "adress": "8fNsw2xDpvXNNEQx4T7RxWWZ1seWTmgYFFG5FtdxZVsC",
          "amount": "13626800559.200924"
        },
        {
          "adress": "99hqYW26oVTfoU5Pq4Lb7BuygobaJgvMJLyoJP2xFNJa",
          "amount": "4361881.74423768"
        }
      ]
    },
    {
      "votePubkey": "J1to3PQfXidUUhprQWgdKkQAMWPJAEqSJ7amkBDE9qhF",
      "sum": "60305343284.82396499901014",
      "wallets": [
        {
          "adress": "9HQLjsNeG5ZTjUjf3xggDxHJRsff1j2kfxkBqeEUGKMe",
          "amount": "1142249479.3164437"
        },
        {
          "adress": "H6tb4zc52Y8kMoSRjfJ48Jv2VRN3X9W19d4mcMMx96rS",
          "amount": "190696352.28031492"
        },
        {
          "adress": "D4Yh5w8fyKiNNEp4ZzqJ1qjGB9TY3RMB3hEQTt67sghG",
          "amount": "1129269318.560422"
        },
        {
          "adress": "FcSFaLnG7PnJzXBHuUrVSNpuNZqic7RX4xDhERNf2qDf",
          "amount": "1028523325.2117099"
        },
        {
          "adress": "jKii4taVkkFoHEHK61yo3jGqot2WhfFrfWhsRJD3Syj",
          "amount": "207095133.49150118"
        },
        {
          "adress": "G3fuYDT3qrg9VFGUU6d2nRiBTry3s8MVsdHuWYt7FTDj",
          "amount": "4562431791.296199"
        },
        {
          "adress": "6wChdchEiawikhbALSBghEeih5iJcHSZYLT42xUtMxcc",
          "amount": "3319536254.794156"
        },
        {
          "adress": "CfVS6ik6fKaWDzsW4zEZ8EAkVAG5g38qoGTJQ9CoA5Xi",
          "amount": "2064523650.710117"
        },
        {
          "adress": "4mAeCBbUuRotXviibCCUQb6suij7fWoVv7sZvwvyG5XW",
          "amount": "12104221840.259562"
        },
        {
          "adress": "AqwRfctVc94mZYrPRuwFqzzYHvzZ8gTCM1Bv69nspCse",
          "amount": "21651297936.244392"
        },
        {
          "adress": "7dWwbj7efvMMFRKHVZ14Ps3kJwAsGgLMgtaGc9RcbAPA",
          "amount": "1240835979.1655731"
        },
        {
          "adress": "CjEXHEHdioS8yguc1T7vcGfstyyVVe6Xc4Tc1ae6E1nm",
          "amount": "1094034516.5469913"
        },
        {
          "adress": "32Ns97YgL23Ct4yGe1fZ4bYHCg6xgDnzs47JqvEmPntP",
          "amount": "1292521594.1870465"
        },
        {
          "adress": "PoLoy5q6vPoFU3BPFoG485LSMsQyXXRDy2Y6AS5qVkX",
          "amount": "18.53799741301014"
        },
        {
          "adress": "7ZsB85RRYN7zAE4FUrdbN2kVUyFJryj4PfX4YbPKb6C2",
          "amount": "227832341.51831588"
        },
        {
          "adress": "Fe9VpeLud7pYL5zRn24H6MNUMMgJrsFRLmHKqHo8nHCh",
          "amount": "2512865243.5478673"
        },
        {
          "adress": "DSeaf7sheji3NFyRu7qtQQANLh9JKrjdXQjErKkbZbVv",
          "amount": "11493779.761564806"
        },
        {
          "adress": "FCakBX9EUZonT4U8oscZDDx3bHyRBxTGWC7F5ZKUsmBS",
          "amount": "6525914729.393791"
        }
      ]
    },
    {
      "votePubkey": "B1w6SZcyvjyp6zEyStcc8u9AxXAh2AbYvNzMmP9rRKE9",
      "sum": "12270265290697.816631332",
      "wallets": [
        {
          "adress": "5XkmK4EemeLcz1qwCW3GPchhphTBirJ4G34cxdDL1hKA",
          "amount": "0"
        },
        {
          "adress": "goodRTLNjkFbP8WmAxPeutixwftKtyM84X37RmZjkss",
          "amount": "28242267.208302252"
        },
        {
          "adress": "F21nsuNL3wrgtMTd5XpyWLSrx8wt8o6XJknSacLz59dn",
          "amount": "7362909698473.107"
        },
        {
          "adress": "AdknutfzabqR1Nh687DSpwMPgaptjom5V62ESURxPAJB",
          "amount": "120470787.90375088"
        },
        {
          "adress": "JEDiNi8XrkSD1avcvKcncoZ7dExC373kuhx4mzqzXBR6",
          "amount": "794360597.803627"
        },
        {
          "adress": "4ko9XSd2srEx1cZhTxmH82K54VzdzASC9a6eCNevggLj",
          "amount": "1104395472223.216"
        },
        {
          "adress": "Div5WiVX5aCwQuquxnemHY92gWetrYJADoUVCoEsaizr",
          "amount": "2041865809059.0981"
        },
        {
          "adress": "GudCATc6qVWqDGeFbFQhD57yjLtfhpNAoiBcGRqjvmKT",
          "amount": "4206342692.055964"
        },
        {
          "adress": "251Hfcw5xGWESY95ibQpnivzUr5D3ZqcybbVp4NMRWTX",
          "amount": "43544067983.97284"
        },
        {
          "adress": "FMVYqwDCmMt44FpBKmWbgopKspEtbwnQQsyR2ueGBuzH",
          "amount": "18501269316.419685"
        },
        {
          "adress": "FY65Rmr1czBNNBR1fPLgTt9T3dR5r82ietVH4phEzGi",
          "amount": "436188174.423768"
        },
        {
          "adress": "E28vfcXPjjbGGmaQgLy5U8oYsQEscYi9byGaDd2F8eCR",
          "amount": "1693452464418.247"
        },
        {
          "adress": "7Rf8zMVTJi3pzFRma1GZLEUh6LpvLkEq55gMQxhtHA7i",
          "amount": "10904704.3605942"
        }
      ]
    },
    {
      "votePubkey": "DriFTm3wM9ugxhCA1K3wVQMSdC4Dv4LNmyZMmZiuHRpp",
      "sum": "11765045701.940993688",
      "wallets": [
        {
          "adress": "FMoTUBbL5dXPHutwL4e2ybKd3LSLDS93PryyUu3pwc16",
          "amount": "42497411.450516805"
        },
        {
          "adress": "9CH6D4dRzChHzqBdXoSt1du4bw4frqUSPFXkPvS3FyLX",
          "amount": "1090513370.0614285"
        },
        {
          "adress": "DKVUgYJboN66rQvsaTuTjemchADRxgeNSbKoqRazUuVE",
          "amount": "3199743247.6994677"
        },
        {
          "adress": "DoTDoUm2yABiYi6rVtQgy3LBxhQWifrmUAHYhsmvywwy",
          "amount": "12425707.791395983"
        },
        {
          "adress": "A7VAUDNm3jDgGBUgheXEEPr22LCxfAzFxQEix4mAihNu",
          "amount": "4145059311.3057475"
        },
        {
          "adress": "7DGbqhApJp6va8GK9ZJq5q7BGJeYTvrzoaBoMXxVHH3a",
          "amount": "1174174780.9798348"
        },
        {
          "adress": "DecXYzt7NdkdtruomaxX3faYJkoThKS5A1iP5ujsp1cU",
          "amount": "2100631872.6526024"
        }
      ]
    },
    {
      "votePubkey": "juicQdAnksqZ5Yb8NQwCLjLWhykvXGktxnQCDvMe6Nx",
      "sum": "25243347373.3330387",
      "wallets": [
        {
          "adress": "VuWDop6xS7ZcJKDh6yngVgKrAL78dGXxWHuVLURZTG9",
          "amount": "1073911495.2743487"
        },
        {
          "adress": "9AfyHBx6n7LP5zobw9urrB3atG4owcpW88th5Zffo7LV",
          "amount": "24169435878.05869"
        }
      ]
    },
    {
      "votePubkey": "gVot34jauJpexBL2YUSPBKsmZ4V2ffmDcRk4yfSEnx8",
      "sum": "9700793834.630009",
      "wallets": [
        {
          "adress": "UBF8B3JmhnwaL9Tbbacz74HM5AYEwZixMHU1kTuUuNt",
          "amount": "9700793834.630009"
        }
      ]
    },
    {
      "votePubkey": "CogentC52e7kktFfWHwsqSmr8LiS1yAtfqhHcftCPcBJ",
      "sum": "2790045501682.59561505",
      "wallets": [
        {
          "adress": "A9qUwgmnDYmS6fQ2ojPgqNKAUnMq4HaMT5hBzZmCCSpi",
          "amount": "379375622.13811505"
        },
        {
          "adress": "5V2h79x27We9qVjEGjbbFzapjqsWafQEcXk7fx6pEgWR",
          "amount": "2789666126060.4575"
        }
      ]
    },
    {
      "votePubkey": "THWfRpcJSC7oDrNMSCcixTZmCHVBTEVQL4qnd1UTD1x",
      "sum": "14341097599198.817171",
      "wallets": [
        {
          "adress": "6c8FaFkrZ4odZXRNTdmDKjbaubajvrMEHRPH31fTB1eb",
          "amount": "81440297209.20345"
        },
        {
          "adress": "AyPzkL3oeHV32gsW3H1P6vrGRZRL16pB924huSUMB8GQ",
          "amount": "22261103099.509678"
        },
        {
          "adress": "2tePPKeFgLQWTojsNQa1fz3jAZPxJtHpoT3Cxr5aJnkU",
          "amount": "10356389792556.979"
        },
        {
          "adress": "BSBNMbBsMBaVQ2hU2tfhDV9WaMLkiw9ATWLcycgGKQ34",
          "amount": "877767262697.7767"
        },
        {
          "adress": "HdngDytahcEW35efiicc3cj3JHoAZqpoTHPM39aQzAmM",
          "amount": "28113913626.619843"
        },
        {
          "adress": "E9qZL6e25Nx7Fne8reJiGNEnohScvB6rGLWEHYiVFmVL",
          "amount": "604614474853.0435"
        },
        {
          "adress": "FB7q9gzPNoqwuXqQMhovm6mn28ZL9vsMRnrFUA8B8fLY",
          "amount": "230339421811.8386"
        },
        {
          "adress": "3zK5Gx5JVLHorAN8q4mAf1LQCZ2Xb871PLPFNYy8RzMQ",
          "amount": "2140171333343.8464"
        }
      ]
    },
    {
      "votePubkey": "EtMSc3MvcDXUr6ChK5GxyFVwTxYA3zqP5XzjE9jwKvSV",
      "sum": "53153663172888.16297474",
      "wallets": [
        {
          "adress": "6iP7Qkz5Mo5yvsrqhkbgZtyhKhrMnadTFd8jojDvKXqn",
          "amount": "45800046375054.72"
        },
        {
          "adress": "8Vv2qW2K7DeqH3nAoJWMJ7wDCu7MJe8VmT3jEcha1VnM",
          "amount": "10904704.3605942"
        },
        {
          "adress": "DEXWBmnNrdineAy2gADspp3Ap51e9bzdNoJemvgKPvhW",
          "amount": "7352288326732.014"
        },
        {
          "adress": "AERY3P5JWpTicGB7XtP5SfNd754vewRipW1bce2R7dLK",
          "amount": "796250222.7701639"
        },
        {
          "adress": "22K33dFGRvQmavyrk1PqUeSC7t9GHUy7Cf52oGsTr5YM",
          "amount": "521316174.29821664"
        }
      ]
    },
    {
      "votePubkey": "Ac1beBKixfNdrTAac7GRaTsJTxLyvgGvJjvy4qQfvyfc",
      "sum": "36624323404.28262154",
      "wallets": [
        {
          "adress": "HmV3ZT6qgdkAjZysJypgHZUdsdLu7QaxY6WFdkdnrYPB",
          "amount": "1043579457.0652049"
        },
        {
          "adress": "GHYFzLxuN1G52KnzmkKeTd5engLJiQaFCpPAbfr2JWBD",
          "amount": "3279154338.542068"
        },
        {
          "adress": "JDdhPwgHxCuJJXrqpvuwcey4VUqnpGiKRRsdKb9xVfB9",
          "amount": "407260224.85762376"
        },
        {
          "adress": "8LyGPy9jPYhtr1FYWG9WAjTzyuZvBMKRsFjnpDGAuLf7",
          "amount": "16959788425.468018"
        },
        {
          "adress": "CZXBPWeUhxxhf9kMzUySQ7hZsHGy3ZzhKGZHGjdGhmAo",
          "amount": "110137514.04200141"
        },
        {
          "adress": "5Lc6KL91cF5wfDV8dbYpGHtu2A5nNLEjzfsGPRaSKzFv",
          "amount": "14709584983.414698"
        },
        {
          "adress": "6yLndF5MWGXhE6F5oZjTcfRxFEzu3RmjCq75THxzfiqq",
          "amount": "114818460.89300747"
        }
      ]
    },
    {
      "votePubkey": "vvvvXsU6iG2enDVvs4KeVqS4YrZczTujSv5p3dSeNHx",
      "sum": "2538593371.18996050613",
      "wallets": [
        {
          "adress": "CAP3AmvvUSTHXG7imdHf31d6kNMJ84uos8Ro4AbhKWHS",
          "amount": "2538515152.8360524"
        },
        {
          "adress": "BWENejsfrBsYM44ELcFywxpn3LCTzKVDws7YoFe6StuN",
          "amount": "78218.35390810613"
        }
      ]
    },
    {
      "votePubkey": "3Xn3K5zeTzs4sURj1PCRaF6rvFg2hPgT49B4SiM998f7",
      "sum": "4973656993939.6340295",
      "wallets": [
        {
          "adress": "35PtfdCD4FTdmZtsx3sEdUBR3viEFXkPb6Np8oLQiN14",
          "amount": "31789696.212315"
        },
        {
          "adress": "GrRWVVcW5atZnxp1Giy1BCtDu1yQLhsDAD1NGQP8vUMa",
          "amount": "169289582.3201145"
        },
        {
          "adress": "84VNUpUyHAB9ShaF9WshrwwCfQYU8toXazPaVcZ1p7B",
          "amount": "2938447682716.2134"
        },
        {
          "adress": "5UUsqaWtfW5BYVcsNpp7dKygbtJjRgrs6wR4fshCQFpu",
          "amount": "2035008231944.8882"
        }
      ]
    },
    {
      "votePubkey": "StepeLdhJ2znRjHcZdjwMWsC4nTRURNKQY8Nca82LJp",
      "sum": "327504426948086.568182892",
      "wallets": [
        {
          "adress": "3g5vvUPFLhYHDbRMriVjNy3cb4hZmjEsxsHi51GbGiEd",
          "amount": "277702848040.6525"
        },
        {
          "adress": "8jGo7FC5sge9radsnoA14YDraburReJaCDVRcHxBq8gR",
          "amount": "101285609033.44841"
        },
        {
          "adress": "BT3k255oVG2Mhw475eBNPMRiEWPVeooST8wt3YDQ7P63",
          "amount": "3601766808.8862243"
        },
        {
          "adress": "DrVWnn1zZQiHf1sfSMoqyTm2ZrDXTzc9xqTY89PN2Q2k",
          "amount": "10731763923.601564"
        },
        {
          "adress": "HTpjsybeTyHtnPVrbj6oHToSVTCJv27HZ9Wrn7m87JUx",
          "amount": "34039981.18993329"
        },
        {
          "adress": "afLfv6Hr8rZQ8ckFs1VhQ548hRqSBaXVWMAkaSUhyEt",
          "amount": "131263527.12185225"
        },
        {
          "adress": "Cw2fRMBy81urPWSjbYdR76Lu238TnThesCv77BJByhbn",
          "amount": "220084375.6853144"
        },
        {
          "adress": "6XVffJaJf7y2yHMWne3mBhNd94UiJ8HSDdZhzzm9cq13",
          "amount": "16500268.023258982"
        },
        {
          "adress": "DanayVvgHg3dFjhJgjNECxU589vGjzmwRBBZ7nCMVzUg",
          "amount": "1103354033.4773877"
        },
        {
          "adress": "J7RhPz5fWeUKoo1aejBYWEHpZ8PaHx4AhiogspUDuG6X",
          "amount": "25070727951.20831"
        },
        {
          "adress": "9EmTXMnCvKzGVV6Sbv2Pnoe2MLhGZ2VcxrTq68twL4Hm",
          "amount": "220745595.51986423"
        },
        {
          "adress": "8RTcZEdX4Juu22LURdSFkKoQ9fgxu74u3b5LSie4f81k",
          "amount": "215812438.12358376"
        },
        {
          "adress": "6xwpVqiuJADLJhZ5ukP3FHFLxg6Efs9nGMEdrzfPHwCA",
          "amount": "654213661.2309899"
        },
        {
          "adress": "2gD2trDSDnJFRve4ZcvPVAic55SWt6CYLbtHvEBzLkoQ",
          "amount": "689466417.8401502"
        },
        {
          "adress": "5m3LKPhNqDKprhJYXX58V29hcGjRwbGMWG9n7YP4gu9e",
          "amount": "1853802681288.9138"
        },
        {
          "adress": "64z9m1Nh7yncyj4nWVH4vRtKL8vSoQiYqwV81kNcSkX",
          "amount": "74196540.82170576"
        },
        {
          "adress": "8hhgpuWGbaEDMVTZsZrM1723r1EU9f4XD7qttWY5HEwc",
          "amount": "84790936768012.53"
        },
        {
          "adress": "GyfiPcfDxFdYHH9yNepmpkPMWjAKeCjomLRUwnk2eRA",
          "amount": "184173026.18488473"
        },
        {
          "adress": "2aWj2T1p42zquWHDBkePWVLeUrs9Prhckf47SfN4V6g7",
          "amount": "7757254808.035935"
        },
        {
          "adress": "FQH9HNVTuid5MbiM42sCaLMozMeTiL7G7hQazPXFxS1F",
          "amount": "10249308465.839956"
        },
        {
          "adress": "8gdSa9ujXHRGf6QaDiJQJRNFTxUMLJjpsjSimfw66W8e",
          "amount": "126039223.93337782"
        },
        {
          "adress": "6GT4kttU36ftv1rz5RoKD3YFk9ArpDUmmRHfABuQeZTh",
          "amount": "116701503.77999228"
        },
        {
          "adress": "8P6bCyJJjpwVbJsuCzKQDPQ5vMdXvTiikuCWfLrJZ7pz",
          "amount": "2505532983.5830894"
        },
        {
          "adress": "Hj561QwPPmNp2K9oKibvNQScpxMXV4LmukuQodMvTkEZ",
          "amount": "10496103376.16415"
        },
        {
          "adress": "3KNZ9i1dLNNqpBTKEkTgUQs6TNCd3bzuy6HwfoXACaRs",
          "amount": "238692372777269.12"
        },
        {
          "adress": "Gps5eSmbejAHXxMwXBSV4vzsNy76i7BgDYYR7d1zfgYi",
          "amount": "5373279090.58039"
        },
        {
          "adress": "3CgXtQKzNk66Q6D5F8KArCdGfBv9r4pYKXVcxvznqLv7",
          "amount": "1705228141445.7913"
        },
        {
          "adress": "9o1rBUx93QQa7YjHudjtr8NVggm7i2MEkkvKnMmWw7bM",
          "amount": "51774884.20278049"
        },
        {
          "adress": "G9J6qwRZmfNprpJJAba1XZoXJaWsjDq1YkueLaza8vXH",
          "amount": "3474020111.0774784"
        }
      ]
    },
    {
      "votePubkey": "5daP6pZoPSak6UEKuRg2HHjvTPpqqwB113oNamGNKuuZ",
      "sum": "41923809680662.1417757",
      "wallets": [
        {
          "adress": "GNFGZdCs9TSsBU37MdzppSw1NrAJoZEbznhWDPVcwoUa",
          "amount": "8647365868527.48"
        },
        {
          "adress": "ASNsejndZQmh3p5taTGEQajzD9Bed9Skx68ETQC4mucC",
          "amount": "27436807279564.547"
        },
        {
          "adress": "5xM3p6sfLopjgDpiXonYfNKTBHj6AN8my4bkKUXBLLuq",
          "amount": "703227796336.1208"
        },
        {
          "adress": "BWw2jAn6fs91T57YkhiS2P5271LZCQBhEKJSeE2Dv58m",
          "amount": "3723208744472.3203"
        },
        {
          "adress": "3Z1jjvAPFXCAm1KoBQM6MaAUm7MhdVUueMxWFWgE1UML",
          "amount": "300386006632.3546"
        },
        {
          "adress": "C1U9ARgYE72KK8rYaXcGcJYU1u8ukFZ2tPWR9EwXunNM",
          "amount": "1963911573.6737757"
        },
        {
          "adress": "Fh9jupsrGWb38qidrmB4kA53cHu2ZnuLZG2ogqMUJQEt",
          "amount": "383105994594.1964"
        },
        {
          "adress": "EKPBjftgaCPswNRK8D2Y31hKFCP43UfHQjoET86hRzgQ",
          "amount": "727744078961.4489"
        }
      ]
    },
    {
      "votePubkey": "mesh3Px7WMi7Dkxke4ZZBULoKHM6sp37wKtg4DwPqPY",
      "sum": "442098509751.562401497",
      "wallets": [
        {
          "adress": "6LriMAjiV39CLatDLvnwH9Y6mJkqcfn9GSCXTzg4dEuG",
          "amount": "260522076671.14093"
        },
        {
          "adress": "ojhV3g32SGtsDiatUaRkvBT1J1TxTYCKCH1998aFKiL",
          "amount": "180289671874.5035"
        },
        {
          "adress": "BWyWxvKv3P8QvtYbEk3sRvY3rXp74JDbGQF6zrVM1FpP",
          "amount": "4267645.470094297"
        },
        {
          "adress": "GmRC6EhKtBEcKM1bjCBzamWDy3qmP5z2Kc9tYjQuc2Pn",
          "amount": "1282493560.4478772"
        }
      ]
    },
    {
      "votePubkey": "86Sw9R6ynPmXnHfwUWinXtq1QoF2KHesfQQyZG5r8sXo",
      "sum": "4299434181.611808",
      "wallets": [
        {
          "adress": "6sB3NAdExQGDYtzvrfjCuWfVdmBE6pnWj1JV48SifsCb",
          "amount": "4299434181.611808"
        }
      ]
    },
    {
      "votePubkey": "sagasJDjjAHND4hien3bbo5xXkzCT5Ss6nKjyUJ45aw",
      "sum": "250753568418.35921936568",
      "wallets": [
        {
          "adress": "DkWc1ZN3QkNMrrm8ZA8UoUZA9vVAb85jshExuwni1Qsw",
          "amount": "134716877457.41374"
        },
        {
          "adress": "6yaWkNc71R5wLp2qbrSdVvtE7Bkmk4SZLRU69pSUHpT7",
          "amount": "43235328633.36304"
        },
        {
          "adress": "4FxZJ67o8PFumLtYJXXGVW2VjzciZoLACtHViwN8oSz9",
          "amount": "36294.12752336568"
        },
        {
          "adress": "37Soxq4xdQkGw6VryrNn2oezALHEs3aFUkYBu8njxKiB",
          "amount": "38301107562.77651"
        },
        {
          "adress": "HF8uDpLL14WxjuSGsFmkF458Myq2Rhd8AtRR6Aw6qnfk",
          "amount": "34500218470.678406"
        }
      ]
    },
    {
      "votePubkey": "B6nDYYLc2iwYqY3zdmavMmU9GjUL2hf79MkufviM2bXv",
      "sum": "13864288684.92753424511884",
      "wallets": [
        {
          "adress": "25ZbUnAsCtD7gNr1Qz4pvFFWEhB88F469BAFgW1zbi7q",
          "amount": "1086638711.5984926"
        },
        {
          "adress": "47Wx6mnnuEGAVqEpz3Sxp1mRsQc72faBg2BxTH8fKoAS",
          "amount": "87791755.25589631"
        },
        {
          "adress": "97WfLeXWdATneuNK1Lh239mGH7U8wUkVyPzGJzMC7yxn",
          "amount": "2550860805.921326"
        },
        {
          "adress": "D5dm8snbrgkh9Eo8NEPNBstCufJk2VqXy9QQpgJ8k7Pb",
          "amount": "1138807262.171513"
        },
        {
          "adress": "BHVxCyb7tnGgPjUJeckr9mKRfjiWuqxsGYxvpEAosNXE",
          "amount": "14490207.139881963"
        },
        {
          "adress": "EP1v5ch4BC6TYbAdPuvFrdwvSgqVTKrYaS5yowufSEsf",
          "amount": "2.18094087211884"
        },
        {
          "adress": "B81jyGwS1oeMb34Ht9sBPxUsm5BuHqLQX2VsLs7dFxu4",
          "amount": "7231727692.7303"
        },
        {
          "adress": "2L8WDXjWQqQnba8rcMVB9LuGjQnK3jSQKgeue7KX4Xzg",
          "amount": "1753972247.9291835"
        }
      ]
    },
    {
      "votePubkey": "91413b9eEvG6UofpSgwdUgH9Lz4QBF1G3J325Bw7JwGR",
      "sum": "1410399621.78708926",
      "wallets": [
        {
          "adress": "JCyncpDM3cKGibbq2dKJEJXRhLUupdVS5RuRqVmu77kn",
          "amount": "1100228937.130438"
        },
        {
          "adress": "3sQHjHaYX2W2xK3cgdCvUg2VzXKuoXAwugdz9U1h2oS4",
          "amount": "310170684.65665126"
        }
      ]
    },
    {
      "votePubkey": "4FsAxdHQ6HmFrDD7yCwsKNApuA67QYSCMoLAy3NfySxJ",
      "sum": "6027678885.30058175",
      "wallets": [
        {
          "adress": "B9BYqnd2RoLYiPVfUMjS7NChxQpVTviToFuaeSj3bLyo",
          "amount": "525749908.22995675"
        },
        {
          "adress": "6tfg3gYiCN6EkjLarLRTwYv2P2hTkvfFrNztvgwqRCNQ",
          "amount": "2230517668.892365"
        },
        {
          "adress": "5woKr7PyRatjp9af9ff2AVvt2njLz2LXHYXVaC7K7rjn",
          "amount": "3271411308.17826"
        }
      ]
    },
    {
      "votePubkey": "GA2t11gJcmuZ4y7pShTzgYDkxVaJaVQJqkVUqojhPPsT",
      "sum": "527312550567.7345756",
      "wallets": [
        {
          "adress": "5f3qnv9bt82JdZC5wokZpJsdMDgZ1F5L2kfuoKFEoCvb",
          "amount": "16126746312.496422"
        },
        {
          "adress": "CtQWAcGd4nuDsixYMGpzrQoxEHt1D55FcZZqySiE28pD",
          "amount": "2003643101.7341557"
        },
        {
          "adress": "CzQUTKwMtXd8us868bzdg3bmYivAAccQJxVsMjdU5ANX",
          "amount": "8671113080.826054"
        },
        {
          "adress": "CcNgWK3zi4HPMPFjYriLHSJML6duRDRwmpcP9Kvixrw4",
          "amount": "9755002215.92931"
        },
        {
          "adress": "9P8VighSgjqdJZfVGzySsGMeWdggRbFvQZkPiKvCD5ty",
          "amount": "10838891351.032566"
        },
        {
          "adress": "9kaUtokHMXKGYNBHju4fUmYSs2zAAWnXQ5dXzv2a4S52",
          "amount": "478848610247.0426"
        },
        {
          "adress": "HQBZZBtYHqDKqBtNKFDDXiZ5pTLNpX2ztRqr8SwECotc",
          "amount": "1068544258.6734679"
        }
      ]
    },
    {
      "votePubkey": "bookLxG3LkSmt4htJ1x9zPw6E34RRMAi7sUn5mM3CNN",
      "sum": "2028820392477.017604",
      "wallets": [
        {
          "adress": "FJCG4aELkU5F5sZGpKifujfJwq7cezFkubovBFho5jVA",
          "amount": "14729043794.782854"
        },
        {
          "adress": "FMqgejiEvqAaa9TAzMX3eP9mCMH9yvFjbJFiEER4UaAq",
          "amount": "9946668348.649233"
        },
        {
          "adress": "4o1M4cisz2BXEUgytKU3XAE7a8stXRFZGiWubxWAzCgv",
          "amount": "3764220708.578263"
        },
        {
          "adress": "91wj1TJHGAoeQNn7s66SgbwU6rgBx7w343mjwA5NYrKb",
          "amount": "4525608607.864664"
        },
        {
          "adress": "9Zss2nH2tA7GUcRfNk3RdwipLvig6qpVZ5RvdCsRiF3T",
          "amount": "378558499483.5317"
        },
        {
          "adress": "BZn3dtZKWi78VbSJ7QCc3rdv7p6WxnUKUxkZskQrHEYN",
          "amount": "1570437960634.4426"
        },
        {
          "adress": "C911HUVfFCC4Ne5Tm3PkDmwGE7ibAkeQ6CUKdc5iHbC2",
          "amount": "46858390899.16829"
        }
      ]
    },
    {
      "votePubkey": "5AC692spnjbegP7ttCXJEzUe8S81sLYsqJd8Ae6Zv1xU",
      "sum": "88389960445.0271",
      "wallets": [
        {
          "adress": "Fi34tJ28GGk29FiZ5YYvUpxGNryP4VzG9GP9GbhCNFEB",
          "amount": "88389960445.0271"
        }
      ]
    },
    {
      "votePubkey": "sw222BfVDABppvydacSCj3JVaPSC83RoRtyvLmr6pNx",
      "sum": "60192278.93177453",
      "wallets": [
        {
          "adress": "E64PiTT7U8ZUWFKdkrBFw1YzdD2bU1gKcuGnBRVqp7M6",
          "amount": "60192278.93177453"
        }
      ]
    },
    {
      "votePubkey": "CwSZ17woioM2bqEbaswZJYvx5pemN6t3shBcU6zqPHyG",
      "sum": "855515912245.69273987",
      "wallets": [
        {
          "adress": "EMCq4vZThPNiGhg2KJJEGCikBvhj9xGuEhw9NzKzLDfZ",
          "amount": "837713264514.8823"
        },
        {
          "adress": "AgoVCkcDbbLcZUEfyQJkbZYRBcpqtJswGETjs7u63AUA",
          "amount": "98422269.54910687"
        },
        {
          "adress": "AMpDEnUDxkT8B4TBxwAvTHifrStDiErrsPfGLvsNphc1",
          "amount": "17704225461.261333"
        }
      ]
    },
    {
      "votePubkey": "gridZ5cMHjWGktAQt6o36NtF7XSv19nJBrW83zmo7BM",
      "sum": "437362123057.53644421003",
      "wallets": [
        {
          "adress": "JDigzj7awgDbZewd1PYeCUyxGmsvrxPrwnk1uWJ7cJw",
          "amount": "428311800089.7215"
        },
        {
          "adress": "FFYpvY3NxC6WWcqjj9oMZZw5xShR3qnfT6wfYJUV3GJX",
          "amount": "102220.69867621003"
        },
        {
          "adress": "3ufaAR6wcNhncX3HNL85hPhSELroHbx8v8icfGVWoy4Z",
          "amount": "9050220747.116268"
        }
      ]
    },
    {
      "votePubkey": "2ayMCC4aizr8RGg5ptXYqu8uoxW1whNek1hE1zaAd58z",
      "sum": "0",
      "wallets": []
    },
    {
      "votePubkey": "9ymU1ayh9mZVyDL4dUUtXKtX1wCaFNzZPGutLJgqzuC1",
      "sum": "18569317314.93013215",
      "wallets": [
        {
          "adress": "6Zg87oCJg919TC1HGkW2Y9w9RwSEhMWoJTEeecnxsZfw",
          "amount": "105150350.00690465"
        },
        {
          "adress": "B7a5S2qivSYv1yv2FBwJ1RCBW31rB4EHCGv77yqWfEJD",
          "amount": "12273412358.792912"
        },
        {
          "adress": "6LyKeCViVfTENLFGXWeLttNsBekch5D5yRuDUcBJQYZ5",
          "amount": "2919343297.9520555"
        },
        {
          "adress": "Dcvdhb7Sq98Tx8QDajYghbW2HSCaVw7YrXUwsctnya4s",
          "amount": "3271411308.17826"
        }
      ]
    },
    {
      "votePubkey": "EpicsoqLdDP8qRn3wQRKTSKAXbjK9dUgFfNPRQS77MQD",
      "sum": "12221528.10694821805942",
      "wallets": [
        {
          "adress": "49GgKPeSsa5FAhQVprQP2KgKiLvSHQPYPpJq2s35XkEe",
          "amount": "1.09047043605942"
        },
        {
          "adress": "AyxGu2NvwYLPMVbzESuZ9oikJeJ1DgHkQrHEPspfUySm",
          "amount": "12221527.016477782"
        }
      ]
    },
    {
      "votePubkey": "EfnywDKqArxK6N6FS9ctsuzNdxfx3pzfXEQE5EevQ1SV",
      "sum": "11700453797142.1906113",
      "wallets": [
        {
          "adress": "3Fv9YppPQ8Z1p3j3vDT8TGhVqmdNnREmQsW94Wvhg8nh",
          "amount": "5221388656449.812"
        },
        {
          "adress": "6XZ8yZZpdBYipuQogDivSCwJD5YHDGovRHuzhYM1ZjAM",
          "amount": "2634217945727.7197"
        },
        {
          "adress": "SUPR82bGgVN27hwY9MA5skbQ7273Lvuxfx8Wh7pG2Nt",
          "amount": "2885098794616.5244"
        },
        {
          "adress": "6pP1s6eGBpY7QKUnDdBtwi8M8CPtR61vUweW1ekQ8mEa",
          "amount": "895705092514.3308"
        },
        {
          "adress": "9qujPqxpfF41in18WSPquH18RuhEwnMB3jCpyAciqTFL",
          "amount": "1357248687.1171613"
        },
        {
          "adress": "CVk5HL6uL61TAQFW5GBR92YGp2hBGGkdcrLZEqZfddFS",
          "amount": "62686059146.68655"
        }
      ]
    },
    {
      "votePubkey": "VotESBSkLKU8vebS6wTR2rzWWJsLc6YThYS6tebPxXq",
      "sum": "7095662407.718771",
      "wallets": [
        {
          "adress": "Gm52wyw9uyRPm4N9DKUNDPfSXdWz6Xg4ePrSMvCPaXUx",
          "amount": "7095662407.718771"
        }
      ]
    },
    {
      "votePubkey": "tri1cHBy47fPyhCvrCf6FnR7Mz6XdSoSBah2FsZVQeT",
      "sum": "69341489.460878472",
      "wallets": [
        {
          "adress": "HawkPXFibs2nzqfL1FUQhuug9ZYrN5ek4snZoxRutSVR",
          "amount": "11982398.845024748"
        },
        {
          "adress": "5sUsbmHqB7m4GhgvTGffy3kbE2Z2gVNhMv9f33jkRjqN",
          "amount": "42999429.144224614"
        },
        {
          "adress": "AojPxAF6hd4h94EzH2fzr5E4g31PvTnWTz49YXkJxw5X",
          "amount": "14359661.47162911"
        }
      ]
    },
    {
      "votePubkey": "adraBKLNY3DL3pg6SJRDYiMA8BsznaWpUdE42X41gbP",
      "sum": "5026714658.473687631",
      "wallets": [
        {
          "adress": "8Hq2X36RFSVtxZRbpBdF22dVsHvJ5tXfpHEDSfz6byG7",
          "amount": "4442465735.267072"
        },
        {
          "adress": "2vYPzqpjn9HqJ8LbkNGwB5Bpnoz6ceFTtw73XeF14gN8",
          "amount": "68626491.9863039"
        },
        {
          "adress": "CQvdwc69vw5VStMQHNCzKRUo8rS5iaxEXjCjcegpnySG",
          "amount": "4530256.922387871"
        },
        {
          "adress": "6fKt1hw6rgr6FNPEEDjQXeKoQWoxoMeWZo7witrFHMbs",
          "amount": "511092174.29792386"
        }
      ]
    },
    {
      "votePubkey": "CNcaYdqkCwxDpKSVK8in5f6kqrTiZ5SuHsHFDqx6jNvu",
      "sum": "26616917.751944378",
      "wallets": [
        {
          "adress": "FFGi5gwZDywKpxtWEHveggBdCfAiyRVxbkQtiJpgEtEZ",
          "amount": "26616917.751944378"
        }
      ]
    },
    {
      "votePubkey": "rapxbkwBSSvtqRFrsY83f51oUuZNuVXci74MuzYhiCy",
      "sum": "0",
      "wallets": []
    },
    {
      "votePubkey": "DfpdmTsSCBPxCDwZwgBMfjjV8mF8xHkGRcXP8dJBVmrq",
      "sum": "204396.6880645416",
      "wallets": [
        {
          "adress": "ATYFVkwAxZNFCZ1SHsHsM5x9ipAnqdzYcNYBXKkGPzH5",
          "amount": "204396.6880645416"
        }
      ]
    },
    {
      "votePubkey": "3xjfK9C9YNcta8MvK1US4sQ3bc6DEjoJoR3qLExGf9xE",
      "sum": "777107922.62701405",
      "wallets": [
        {
          "adress": "6APKYMHdHTFPSdJeq95jWAuAc1zfGAisZdL13hjGdtyx",
          "amount": "257372785.42851555"
        },
        {
          "adress": "9L9GBaQLaPqFxdSQsT4MWuZpCQdxuUCsV1eD8Z7wUP1i",
          "amount": "519735137.1984985"
        }
      ]
    },
    {
      "votePubkey": "Gvt8s5Bwnhg4G27VbnT1Zkfh7Jsztq6CNvZcc5anPonS",
      "sum": "34250191.175892469",
      "wallets": [
        {
          "adress": "6VHhJXcj9BnqyQFAixH5LWUz2LWCWAWumRpSXjs2ghkL",
          "amount": "13871937.664397173"
        },
        {
          "adress": "4nQ5VWQga2HmLr45VWQ3s9CZMAoWHmRXzGwE1oSpcMZh",
          "amount": "20378253.511495296"
        }
      ]
    },
    {
      "votePubkey": "EsSodfiCfuM4ANfpPAunwj3wo8RaoRrZR9yY79CoXoUV",
      "sum": "0",
      "wallets": []
    },
    {
      "votePubkey": "ELE2xaC6i6pmeu7bfrYjBv4whBeTAbgwcg5hf2ythiBs",
      "sum": "7392359451.218737",
      "wallets": [
        {
          "adress": "4qgwNbU8xK5APASwDEP92ijbsnffs6foSkCuRvGc1gUX",
          "amount": "7392359451.218737"
        }
      ]
    },
    {
      "votePubkey": "21wUViiyG1g47VZ39ZZsSkFX9nu6bkyfy6jryHGD2TUB",
      "sum": "225051236.25136214",
      "wallets": [
        {
          "adress": "DUmJ5yKiNJ7Q9GtN2cmd95no4opuiNHKzTBHTdGvaSPC",
          "amount": "225051236.25136214"
        }
      ]
    },
    {
      "votePubkey": "4565LXcdfFzN9bHqo1eCZRogsgQREf4oiyjoKuWu7XTX",
      "sum": "0",
      "wallets": []
    },
    {
      "votePubkey": "CHiaohVV2SQCFhiYP73iQzWT6HxnZqnAZJJqAYTeLAo",
      "sum": "0",
      "wallets": []
    },
    {
      "votePubkey": "5iZ5PQPy5Z9XDnkfoWPi6nvUgtxWnRFwZ36WaftPuaVM",
      "sum": "7346438003432.749",
      "wallets": [
        {
          "adress": "5NWWFWbJEZcFPrmhcgnKSphdpRmCyZ8bCiftABaFCCSM",
          "amount": "7346438003432.749"
        }
      ]
    },
    {
      "votePubkey": "76DafWkJ6pGK2hoD41HjrM4xTBhfKqrDYDazv13n5ir1",
      "sum": "61466644.12123013",
      "wallets": [
        {
          "adress": "7KGo4xjmztVfFwg7iYV5zfXLPwLFs3m92aau3Z3mjkkJ",
          "amount": "61466644.12123013"
        }
      ]
    },
    {
      "votePubkey": "o27rnqfNHPwHsRp2xPXXwWzn2q2dGxn6UD4Rt5KMU5h",
      "sum": "0",
      "wallets": []
    },
    {
      "votePubkey": "HMk1qny4fvMnajErxjXG5kT89JKV4cx1PKa9zhQBF9ib",
      "sum": "442364447569.42175",
      "wallets": [
        {
          "adress": "9qCyPu7sLjnwgcbHYY76eqvtjsrdDxis9nn1sjD8CyJo",
          "amount": "442364447569.42175"
        }
      ]
    },
    {
      "votePubkey": "6oscGUEkXE8fyWoC4czRKbM1cuLkJNtgRsX1Un6w88Vf",
      "sum": "0",
      "wallets": []
    },
    {
      "votePubkey": "3iPuTgpWaaC6jYEY7kd993QBthGsQTK3yPCrNJyPMhCD",
      "sum": "0",
      "wallets": []
    },
    {
      "votePubkey": "phz34EcgWRCT9otPzRS2JtSzVHxQJk4SovqJvV1TQk8",
      "sum": "0",
      "wallets": []
    },
    {
      "votePubkey": "BANX7gZwUYFiFJKX9i2hHygy6DxixPutQoQW1U1oBdwt",
      "sum": "3758155788605.274011",
      "wallets": [
        {
          "adress": "8gpJoXXcYHKKe7ZVihEmP99SRAkqEmbsEb4Qr5fqFQga",
          "amount": "4138315106.0616117"
        },
        {
          "adress": "51tSwztLZjogdEaqYLE1yAyyKvwZiPxX9soRUYcjwFk",
          "amount": "10113498464.319391"
        },
        {
          "adress": "GEXmcNKnimgbizmGJSrZrvsrpDDyfUkCniM5KtFS3WN3",
          "amount": "3740978379358.9443"
        },
        {
          "adress": "3ZGqvJZdchB3G9ruDeumyTLHkgWVpH1i11EkFp5N2PdH",
          "amount": "1009339599.1871645"
        },
        {
          "adress": "6ga7pDfzhttVfxoxfDjG3r26cU21NomtrFuASxxpej6d",
          "amount": "1916256076.7615438"
        }
      ]
    },
    {
      "votePubkey": "9Gko8QZBbV5SrEvHKtQHcMrGGSfgFP3KJUozEGifu25x",
      "sum": "3557890229.313583",
      "wallets": [
        {
          "adress": "r1hUzERZaASRpVZTNmNK6KVwePyGHSMunk5ApjPVFeT",
          "amount": "3557890229.313583"
        }
      ]
    },
    {
      "votePubkey": "323d4ZiSqS1PwGwpJwD88jNPaGqkm7YYW2tJt2T8iFzo",
      "sum": "0",
      "wallets": []
    },
    {
      "votePubkey": "ChaosDKeBjU22B4nnvYWXyTRPuWTzJBR4m3QPfBw6Tta",
      "sum": "0",
      "wallets": []
    },
    {
      "votePubkey": "EJHf5N9is5spAF5Kz384tTvTV3CwTka6qzUoZrYm53SV",
      "sum": "0",
      "wallets": []
    },
    {
      "votePubkey": "nateBZg7oHVPLB2samBLkKvfzedU3ALZBexMFPMKjn1",
      "sum": "321724751.0762736",
      "wallets": [
        {
          "adress": "D9nwjDWLAZfddxFMrvLXSukT1edwRskASrqWkFWG2LHL",
          "amount": "321724751.0762736"
        }
      ]
    },
    {
      "votePubkey": "6JfBwvcz5QUKQJ37BMKTLrf968DDJBtwoZLw19aHwFtQ",
      "sum": "657917762687.2606",
      "wallets": [
        {
          "adress": "FfihYCMBM6Gv39Nvs15hmigtBVbXVEFX8WcaZWxPRoi3",
          "amount": "657917762687.2606"
        }
      ]
    },
    {
      "votePubkey": "4m1PbxzwLdUnEwog3T9UKxgjktgriHgE1CfAhMqDw7Xx",
      "sum": "2093016086207.7612",
      "wallets": [
        {
          "adress": "2pR4ejyJR7c6FfoYUnXxt7NW5BeE42gCRraS6xom38aq",
          "amount": "2093016086207.7612"
        }
      ]
    },
    {
      "votePubkey": "mythxna3hpzXSbaseyR12vu5Vvym1HxS92eCgXLvY7w",
      "sum": "1250591060.5213039",
      "wallets": [
        {
          "adress": "8AThr4fWUn4jALMtCvZrMR8RXZxR6nfnjeEK7w5gebR7",
          "amount": "709692781.9055476"
        },
        {
          "adress": "HKiNeY14zzN5y9pVh4MQqphopzbV6cyTkPtPyC17XtHt",
          "amount": "540898278.6157563"
        }
      ]
    },
    {
      "votePubkey": "Luck3DN3HhkV6oc7rPQ1hYGgU3b5AhdKW9o1ob6AyU9",
      "sum": "0",
      "wallets": []
    },
    {
      "votePubkey": "burnn86ebxJnhtk3cfpHoZxy5nUaC3K9U8VwzgqhEEt",
      "sum": "21531544639.721104",
      "wallets": [
        {
          "adress": "Gc456YZeJ9GLe2C665y9DRE5hEtNReYNtqDtR6HDdozE",
          "amount": "21531544639.721104"
        }
      ]
    },
    {
      "votePubkey": "PineDoC593nrX16W8ZLWfF5Evb6otv7fRfZMLjPAHe3",
      "sum": "0",
      "wallets": []
    },
    {
      "votePubkey": "Luna8BkZNpZ9DKmszrZYPvFpTr4eJJfxxTnGDwTrYkv",
      "sum": "66379093104.44614",
      "wallets": [
        {
          "adress": "9uSXTznkRQnuNvutLjDgfxmXfKQv1ojvrFTjoPKh1mAA",
          "amount": "15575285077.50238"
        },
        {
          "adress": "B3RDMvAdKDu5zPJvBkR2Ardn7GNzAnGaM1WjhmkK38X6",
          "amount": "50803808026.94376"
        }
      ]
    },
    {
      "votePubkey": "Hx4UJCvf8amGeuW9fPFfTckRoznDHxPSYiU9HuUSZKLT",
      "sum": "7322823124.133636",
      "wallets": [
        {
          "adress": "BNQgmcJhQuBj9X9s5jzyAiuBHnMzat9ruci1H8FGACpG",
          "amount": "7322823124.133636"
        }
      ]
    },
    {
      "votePubkey": "EARNynHRWg6GfyJCmrrizcZxARB3HVzcaasvNa8kBS72",
      "sum": "9514887382498.742",
      "wallets": [
        {
          "adress": "NMnh1gSaTYLhZjadfJ5haaj4wGSVRnTGk1gXjTgMpfe",
          "amount": "9514887382498.742"
        }
      ]
    },
    {
      "votePubkey": "SoLiDDVm88uWUMk2rQpG7B9wC55a6xveYEz3JnS6tzC",
      "sum": "177460511236.21912",
      "wallets": [
        {
          "adress": "3QkPVUxwHaZ3FKYhykyQWLgJCyUvn5hobYYfXK5RvBKp",
          "amount": "177460511236.21912"
        }
      ]
    },
    {
      "votePubkey": "ACCRENAtboR1MyyoiPvwNZNkjt1GcLARrACh6hZXdddF",
      "sum": "0",
      "wallets": []
    },
    {
      "votePubkey": "GREEDkpTvpKzcGvBu9qd36yk6BfjTWPShB67gLWuixMv",
      "sum": "0",
      "wallets": []
    },
    {
      "votePubkey": "steakxfubt37xYdvuXz7BV5Uhhhk1FyJx9zGHfDcTVr",
      "sum": "0",
      "wallets": []
    },
    {
      "votePubkey": "8DHFGo3fDB8GudbNLZEyExLzXQPwvY4twybPbxwDnffx",
      "sum": "0",
      "wallets": []
    },
    {
      "votePubkey": "fVotEjqpmpQYgyVyBCwYm62BKqqTQNE6SpYnRmdBazH",
      "sum": "5713214.518011234",
      "wallets": [
        {
          "adress": "HPqJfzZp95b9gMUVE546kAMqLH9ZDmhsRnB8Z8XowZy2",
          "amount": "5713214.518011234"
        }
      ]
    },
    {
      "votePubkey": "mintrNtxN3PhAB45Pt41XqyKghTTpqcoBkQTZqh96iR",
      "sum": "1173375266.5941133",
      "wallets": [
        {
          "adress": "A443JrZHBGqoWyzgXcXnMBQBsQMXY2vqx4KgY4xaMgv2",
          "amount": "1173375266.5941133"
        }
      ]
    },
    {
      "votePubkey": "AZUYzQX7nrbN1iE25YsSCSZAywZcyr1C1anMnwZtaqX9",
      "sum": "2248016726315.8467",
      "wallets": [
        {
          "adress": "DnEG4oLkFXn95ujn4nYPvgYHQeq9zRFpJRzBfMqqwwML",
          "amount": "2248016726315.8467"
        }
      ]
    }
  ]
}